{
    "cost": 4.710974589994896,
    "frame_id": "/map",
    "goal_position": [
        2.567359756802097,
        1.8634832281407525,
        0.0
    ],
    "path": [
        {
            "qw": 1.0,
            "qx": 0.0,
            "qy": 0.0,
            "qz": 0.0,
            "x": 2.567359756802097,
            "y": 1.8634832281407525,
            "z": 0.0
        },
        {
            "qw": 1.0,
            "qx": 0.0,
            "qy": 0.0,
            "qz": 0.0,
            "x": 2.550000127404928,
            "y": 1.8500001169741154,
            "z": 0.0
        },
        {
            "qw": 1.0,
            "qx": 0.0,
            "qy": 0.0,
            "qz": 0.0,
            "x": 2.6000001281499863,
            "y": 1.9000001177191734,
            "z": 0.0
        },
        {
            "qw": 1.0,
            "qx": 0.0,
            "qy": 0.0,
            "qz": 0.0,
            "x": 2.595425543120882,
            "y": 1.9245782125678375,
            "z": 0.0
        },
        {
            "qw": 1.0,
            "qx": 0.0,
            "qy": 0.0,
            "qz": 0.0,
            "x": 2.5909417478880528,
            "y": 1.9491723291452558,
            "z": 0.0
        },
        {
            "qw": 1.0,
            "qx": 0.0,
            "qy": 0.0,
            "qz": 0.0,
            "x": 2.586466344989333,
            "y": 1.9737687345410677,
            "z": 0.0
        },
        {
            "qw": 1.0,
            "qx": 0.0,
            "qy": 0.0,
            "qz": 0.0,
            "x": 2.581936773388634,
            "y": 1.9983552217238412,
            "z": 0.0
        },
        {
            "qw": 1.0,
            "qx": 0.0,
            "qy": 0.0,
            "qz": 0.0,
            "x": 2.577304204960228,
            "y": 2.022921872480538,
            "z": 0.0
        },
        {
            "qw": 1.0,
            "qx": 0.0,
            "qy": 0.0,
            "qz": 0.0,
            "x": 2.5724351252978295,
            "y": 2.0474435098088293,
            "z": 0.0
        },
        {
            "qw": 1.0,
            "qx": 0.0,
            "qy": 0.0,
            "qz": 0.0,
            "x": 2.5672890986098196,
            "y": 2.0719079266772837,
            "z": 0.0
        },
        {
            "qw": 1.0,
            "qx": 0.0,
            "qy": 0.0,
            "qz": 0.0,
            "x": 2.5618104303152904,
            "y": 2.096300627236076,
            "z": 0.0
        },
        {
            "qw": 1.0,
            "qx": 0.0,
            "qy": 0.0,
            "qz": 0.0,
            "x": 2.5559686028356623,
            "y": 2.1206078785748446,
            "z": 0.0
        },
        {
            "qw": 1.0,
            "qx": 0.0,
            "qy": 0.0,
            "qz": 0.0,
            "x": 2.549744542684323,
            "y": 2.1448212883594806,
            "z": 0.0
        },
        {
            "qw": 1.0,
            "qx": 0.0,
            "qy": 0.0,
            "qz": 0.0,
            "x": 2.5446244559381057,
            "y": 2.1692910458041865,
            "z": 0.0
        },
        {
            "qw": 1.0,
            "qx": 0.0,
            "qy": 0.0,
            "qz": 0.0,
            "x": 2.5391114553676744,
            "y": 2.193675354028869,
            "z": 0.0
        },
        {
            "qw": 1.0,
            "qx": 0.0,
            "qy": 0.0,
            "qz": 0.0,
            "x": 2.533200963336242,
            "y": 2.2179665836388835,
            "z": 0.0
        },
        {
            "qw": 1.0,
            "qx": 0.0,
            "qy": 0.0,
            "qz": 0.0,
            "x": 2.5268563587495123,
            "y": 2.2421487129054753,
            "z": 0.0
        },
        {
            "qw": 1.0,
            "qx": 0.0,
            "qy": 0.0,
            "qz": 0.0,
            "x": 2.5200539904840866,
            "y": 2.2662049571604257,
            "z": 0.0
        },
        {
            "qw": 1.0,
            "qx": 0.0,
            "qy": 0.0,
            "qz": 0.0,
            "x": 2.512722905169767,
            "y": 2.290106324704084,
            "z": 0.0
        },
        {
            "qw": 1.0,
            "qx": 0.0,
            "qy": 0.0,
            "qz": 0.0,
            "x": 2.5048211411360057,
            "y": 2.3138245867762635,
            "z": 0.0
        },
        {
            "qw": 1.0,
            "qx": 0.0,
            "qy": 0.0,
            "qz": 0.0,
            "x": 2.4963273360777976,
            "y": 2.3373376181324943,
            "z": 0.0
        },
        {
            "qw": 1.0,
            "qx": 0.0,
            "qy": 0.0,
            "qz": 0.0,
            "x": 2.487896092055678,
            "y": 2.3608727747331955,
            "z": 0.0
        },
        {
            "qw": 1.0,
            "qx": 0.0,
            "qy": 0.0,
            "qz": 0.0,
            "x": 2.4790940594538142,
            "y": 2.3842721281092167,
            "z": 0.0
        },
        {
            "qw": 1.0,
            "qx": 0.0,
            "qy": 0.0,
            "qz": 0.0,
            "x": 2.469887668935769,
            "y": 2.407515078895017,
            "z": 0.0
        },
        {
            "qw": 1.0,
            "qx": 0.0,
            "qy": 0.0,
            "qz": 0.0,
            "x": 2.4602624246517166,
            "y": 2.430587894180235,
            "z": 0.0
        },
        {
            "qw": 1.0,
            "qx": 0.0,
            "qy": 0.0,
            "qz": 0.0,
            "x": 2.450208408388619,
            "y": 2.45347684105451,
            "z": 0.0
        },
        {
            "qw": 1.0,
            "qx": 0.0,
            "qy": 0.0,
            "qz": 0.0,
            "x": 2.439701206083612,
            "y": 2.476162083091765,
            "z": 0.0
        },
        {
            "qw": 1.0,
            "qx": 0.0,
            "qy": 0.0,
            "qz": 0.0,
            "x": 2.429486209593506,
            "y": 2.498980076595842,
            "z": 0.0
        },
        {
            "qw": 1.0,
            "qx": 0.0,
            "qy": 0.0,
            "qz": 0.0,
            "x": 2.419096499966031,
            "y": 2.521718724395612,
            "z": 0.0
        },
        {
            "qw": 1.0,
            "qx": 0.0,
            "qy": 0.0,
            "qz": 0.0,
            "x": 2.408269626025401,
            "y": 2.544252141479433,
            "z": 0.0
        },
        {
            "qw": 1.0,
            "qx": 0.0,
            "qy": 0.0,
            "qz": 0.0,
            "x": 2.3970132171662613,
            "y": 2.5665749872710535,
            "z": 0.0
        },
        {
            "qw": 1.0,
            "qx": 0.0,
            "qy": 0.0,
            "qz": 0.0,
            "x": 2.3869576750242345,
            "y": 2.589463171205864,
            "z": 0.0
        },
        {
            "qw": 1.0,
            "qx": 0.0,
            "qy": 0.0,
            "qz": 0.0,
            "x": 2.3772279080335466,
            "y": 2.612492498941606,
            "z": 0.0
        },
        {
            "qw": 1.0,
            "qx": 0.0,
            "qy": 0.0,
            "qz": 0.0,
            "x": 2.3672395045643952,
            "y": 2.6354104375155316,
            "z": 0.0
        },
        {
            "qw": 1.0,
            "qx": 0.0,
            "qy": 0.0,
            "qz": 0.0,
            "x": 2.3564545922943125,
            "y": 2.657964453964894,
            "z": 0.0
        },
        {
            "qw": 1.0,
            "qx": 0.0,
            "qy": 0.0,
            "qz": 0.0,
            "x": 2.343760042544602,
            "y": 2.679501472108086,
            "z": 0.0
        },
        {
            "qw": 1.0,
            "qx": 0.0,
            "qy": 0.0,
            "qz": 0.0,
            "x": 2.3310021688193387,
            "y": 2.701001106217518,
            "z": 0.0
        },
        {
            "qw": 1.0,
            "qx": 0.0,
            "qy": 0.0,
            "qz": 0.0,
            "x": 2.317701082195356,
            "y": 2.72216962459936,
            "z": 0.0
        },
        {
            "qw": 1.0,
            "qx": 0.0,
            "qy": 0.0,
            "qz": 0.0,
            "x": 2.301877717701757,
            "y": 2.7415238729346356,
            "z": 0.0
        },
        {
            "qw": 1.0,
            "qx": 0.0,
            "qy": 0.0,
            "qz": 0.0,
            "x": 2.2834328932081576,
            "y": 2.758400093889236,
            "z": 0.0
        },
        {
            "qw": 1.0,
            "qx": 0.0,
            "qy": 0.0,
            "qz": 0.0,
            "x": 2.263828400728528,
            "y": 2.773912942020786,
            "z": 0.0
        },
        {
            "qw": 1.0,
            "qx": 0.0,
            "qy": 0.0,
            "qz": 0.0,
            "x": 2.2440980232372567,
            "y": 2.789266335804257,
            "z": 0.0
        },
        {
            "qw": 1.0,
            "qx": 0.0,
            "qy": 0.0,
            "qz": 0.0,
            "x": 2.223107269750642,
            "y": 2.8028451323933155,
            "z": 0.0
        },
        {
            "qw": 1.0,
            "qx": 0.0,
            "qy": 0.0,
            "qz": 0.0,
            "x": 2.2010895997448188,
            "y": 2.814686715821722,
            "z": 0.0
        },
        {
            "qw": 1.0,
            "qx": 0.0,
            "qy": 0.0,
            "qz": 0.0,
            "x": 2.178077056677296,
            "y": 2.8244546297856346,
            "z": 0.0
        },
        {
            "qw": 1.0,
            "qx": 0.0,
            "qy": 0.0,
            "qz": 0.0,
            "x": 2.1544709467063967,
            "y": 2.832685983668057,
            "z": 0.0
        },
        {
            "qw": 1.0,
            "qx": 0.0,
            "qy": 0.0,
            "qz": 0.0,
            "x": 2.130299498592308,
            "y": 2.8390694981674756,
            "z": 0.0
        },
        {
            "qw": 1.0,
            "qx": 0.0,
            "qy": 0.0,
            "qz": 0.0,
            "x": 2.105829741147602,
            "y": 2.844190347853157,
            "z": 0.0
        },
        {
            "qw": 1.0,
            "qx": 0.0,
            "qy": 0.0,
            "qz": 0.0,
            "x": 2.081094480769252,
            "y": 2.84781736206736,
            "z": 0.0
        },
        {
            "qw": 1.0,
            "qx": 0.0,
            "qy": 0.0,
            "qz": 0.0,
            "x": 2.056200528982288,
            "y": 2.8501237280685245,
            "z": 0.0
        },
        {
            "qw": 1.0,
            "qx": 0.0,
            "qy": 0.0,
            "qz": 0.0,
            "x": 2.031254697311738,
            "y": 2.851765573796115,
            "z": 0.0
        },
        {
            "qw": 1.0,
            "qx": 0.0,
            "qy": 0.0,
            "qz": 0.0,
            "x": 2.0062913180335045,
            "y": 2.8531167395877333,
            "z": 0.0
        },
        {
            "qw": 1.0,
            "qx": 0.0,
            "qy": 0.0,
            "qz": 0.0,
            "x": 1.9813157317238392,
            "y": 2.854218424174462,
            "z": 0.0
        },
        {
            "qw": 1.0,
            "qx": 0.0,
            "qy": 0.0,
            "qz": 0.0,
            "x": 1.9563309901406,
            "y": 2.8551026710138103,
            "z": 0.0
        },
        {
            "qw": 1.0,
            "qx": 0.0,
            "qy": 0.0,
            "qz": 0.0,
            "x": 1.9313409079811095,
            "y": 2.855805338260609,
            "z": 0.0
        },
        {
            "qw": 1.0,
            "qx": 0.0,
            "qy": 0.0,
            "qz": 0.0,
            "x": 1.9064675555596864,
            "y": 2.8583154090987932,
            "z": 0.0
        },
        {
            "qw": 1.0,
            "qx": 0.0,
            "qy": 0.0,
            "qz": 0.0,
            "x": 1.8815987807750503,
            "y": 2.8608720192443116,
            "z": 0.0
        },
        {
            "qw": 1.0,
            "qx": 0.0,
            "qy": 0.0,
            "qz": 0.0,
            "x": 1.856859705699378,
            "y": 2.864476908214044,
            "z": 0.0
        },
        {
            "qw": 1.0,
            "qx": 0.0,
            "qy": 0.0,
            "qz": 0.0,
            "x": 1.8320878242267327,
            "y": 2.867843760070855,
            "z": 0.0
        },
        {
            "qw": 1.0,
            "qx": 0.0,
            "qy": 0.0,
            "qz": 0.0,
            "x": 1.8071358890404667,
            "y": 2.866295755897397,
            "z": 0.0
        },
        {
            "qw": 1.0,
            "qx": 0.0,
            "qy": 0.0,
            "qz": 0.0,
            "x": 1.782218286130103,
            "y": 2.8642625222245215,
            "z": 0.0
        },
        {
            "qw": 1.0,
            "qx": 0.0,
            "qy": 0.0,
            "qz": 0.0,
            "x": 1.7579423153093785,
            "y": 2.8582909950359294,
            "z": 0.0
        },
        {
            "qw": 1.0,
            "qx": 0.0,
            "qy": 0.0,
            "qz": 0.0,
            "x": 1.7340523918576878,
            "y": 2.8509240515667784,
            "z": 0.0
        },
        {
            "qw": 1.0,
            "qx": 0.0,
            "qy": 0.0,
            "qz": 0.0,
            "x": 1.711247368324507,
            "y": 2.8406793004375572,
            "z": 0.0
        },
        {
            "qw": 1.0,
            "qx": 0.0,
            "qy": 0.0,
            "qz": 0.0,
            "x": 1.6896050645352148,
            "y": 2.828165567340932,
            "z": 0.0
        },
        {
            "qw": 1.0,
            "qx": 0.0,
            "qy": 0.0,
            "qz": 0.0,
            "x": 1.6658906171603576,
            "y": 2.820251596275739,
            "z": 0.0
        },
        {
            "qw": 1.0,
            "qx": 0.0,
            "qy": 0.0,
            "qz": 0.0,
            "x": 1.642099875839051,
            "y": 2.812569558807752,
            "z": 0.0
        },
        {
            "qw": 1.0,
            "qx": 0.0,
            "qy": 0.0,
            "qz": 0.0,
            "x": 1.6182114782662893,
            "y": 2.8051988006412785,
            "z": 0.0
        },
        {
            "qw": 1.0,
            "qx": 0.0,
            "qy": 0.0,
            "qz": 0.0,
            "x": 1.59420635095546,
            "y": 2.798215615722768,
            "z": 0.0
        },
        {
            "qw": 1.0,
            "qx": 0.0,
            "qy": 0.0,
            "qz": 0.0,
            "x": 1.5692238981906144,
            "y": 2.79728559251555,
            "z": 0.0
        },
        {
            "qw": 1.0,
            "qx": 0.0,
            "qy": 0.0,
            "qz": 0.0,
            "x": 1.5444390467470726,
            "y": 2.794009530455014,
            "z": 0.0
        },
        {
            "qw": 1.0,
            "qx": 0.0,
            "qy": 0.0,
            "qz": 0.0,
            "x": 1.520417897707489,
            "y": 2.787084328935805,
            "z": 0.0
        },
        {
            "qw": 1.0,
            "qx": 0.0,
            "qy": 0.0,
            "qz": 0.0,
            "x": 1.4971207782197098,
            "y": 2.778016030460833,
            "z": 0.0
        },
        {
            "qw": 1.0,
            "qx": 0.0,
            "qy": 0.0,
            "qz": 0.0,
            "x": 1.4743561904781473,
            "y": 2.767682015414266,
            "z": 0.0
        },
        {
            "qw": 1.0,
            "qx": 0.0,
            "qy": 0.0,
            "qz": 0.0,
            "x": 1.4523095287726733,
            "y": 2.7558946006878386,
            "z": 0.0
        },
        {
            "qw": 1.0,
            "qx": 0.0,
            "qy": 0.0,
            "qz": 0.0,
            "x": 1.4309800301638234,
            "y": 2.7428544393607126,
            "z": 0.0
        },
        {
            "qw": 1.0,
            "qx": 0.0,
            "qy": 0.0,
            "qz": 0.0,
            "x": 1.4071984441160907,
            "y": 2.750563179709957,
            "z": 0.0
        },
        {
            "qw": 1.0,
            "qx": 0.0,
            "qy": 0.0,
            "qz": 0.0,
            "x": 1.3827256349135268,
            "y": 2.755669533545813,
            "z": 0.0
        },
        {
            "qw": 1.0,
            "qx": 0.0,
            "qy": 0.0,
            "qz": 0.0,
            "x": 1.3577256345409978,
            "y": 2.755773293312984,
            "z": 0.0
        },
        {
            "qw": 1.0,
            "qx": 0.0,
            "qy": 0.0,
            "qz": 0.0,
            "x": 1.3327469964734746,
            "y": 2.7547318809439503,
            "z": 0.0
        },
        {
            "qw": 1.0,
            "qx": 0.0,
            "qy": 0.0,
            "qz": 0.0,
            "x": 1.3085068838075813,
            "y": 2.7486169211360334,
            "z": 0.0
        },
        {
            "qw": 1.0,
            "qx": 0.0,
            "qy": 0.0,
            "qz": 0.0,
            "x": 1.284323991601525,
            "y": 2.7422761312466264,
            "z": 0.0
        },
        {
            "qw": 1.0,
            "qx": 0.0,
            "qy": 0.0,
            "qz": 0.0,
            "x": 1.262996018871604,
            "y": 2.729233681101107,
            "z": 0.0
        },
        {
            "qw": 1.0,
            "qx": 0.0,
            "qy": 0.0,
            "qz": 0.0,
            "x": 1.2431817180392386,
            "y": 2.7139893876610586,
            "z": 0.0
        },
        {
            "qw": 1.0,
            "qx": 0.0,
            "qy": 0.0,
            "qz": 0.0,
            "x": 1.222171128126547,
            "y": 2.7004411086505797,
            "z": 0.0
        },
        {
            "qw": 1.0,
            "qx": 0.0,
            "qy": 0.0,
            "qz": 0.0,
            "x": 1.2030572057225868,
            "y": 2.6843270642210086,
            "z": 0.0
        },
        {
            "qw": 1.0,
            "qx": 0.0,
            "qy": 0.0,
            "qz": 0.0,
            "x": 1.178643142858789,
            "y": 2.6897111280219406,
            "z": 0.0
        },
        {
            "qw": 1.0,
            "qx": 0.0,
            "qy": 0.0,
            "qz": 0.0,
            "x": 1.1536812894594846,
            "y": 2.6883431775621034,
            "z": 0.0
        },
        {
            "qw": 1.0,
            "qx": 0.0,
            "qy": 0.0,
            "qz": 0.0,
            "x": 1.1289475549600638,
            "y": 2.6847039563164685,
            "z": 0.0
        },
        {
            "qw": 1.0,
            "qx": 0.0,
            "qy": 0.0,
            "qz": 0.0,
            "x": 1.1056962118401543,
            "y": 2.6755174022245,
            "z": 0.0
        },
        {
            "qw": 1.0,
            "qx": 0.0,
            "qy": 0.0,
            "qz": 0.0,
            "x": 1.0834550005712345,
            "y": 2.664101539017281,
            "z": 0.0
        },
        {
            "qw": 1.0,
            "qx": 0.0,
            "qy": 0.0,
            "qz": 0.0,
            "x": 1.058812818807553,
            "y": 2.659887061415418,
            "z": 0.0
        },
        {
            "qw": 1.0,
            "qx": 0.0,
            "qy": 0.0,
            "qz": 0.0,
            "x": 1.034179029377981,
            "y": 2.6556237556878273,
            "z": 0.0
        },
        {
            "qw": 1.0,
            "qx": 0.0,
            "qy": 0.0,
            "qz": 0.0,
            "x": 1.0109047980741366,
            "y": 2.6464967108740893,
            "z": 0.0
        },
        {
            "qw": 1.0,
            "qx": 0.0,
            "qy": 0.0,
            "qz": 0.0,
            "x": 0.9863717166538777,
            "y": 2.6416879034293856,
            "z": 0.0
        },
        {
            "qw": 1.0,
            "qx": 0.0,
            "qy": 0.0,
            "qz": 0.0,
            "x": 0.9613717162813487,
            "y": 2.641706976915998,
            "z": 0.0
        },
        {
            "qw": 1.0,
            "qx": 0.0,
            "qy": 0.0,
            "qz": 0.0,
            "x": 0.9363717159088196,
            "y": 2.641584906601679,
            "z": 0.0
        },
        {
            "qw": 1.0,
            "qx": 0.0,
            "qy": 0.0,
            "qz": 0.0,
            "x": 0.9113740043546841,
            "y": 2.6412751531790946,
            "z": 0.0
        },
        {
            "qw": 1.0,
            "qx": 0.0,
            "qy": 0.0,
            "qz": 0.0,
            "x": 0.886377055740013,
            "y": 2.6408730840813064,
            "z": 0.0
        },
        {
            "qw": 1.0,
            "qx": 0.0,
            "qy": 0.0,
            "qz": 0.0,
            "x": 0.8613839218226644,
            "y": 2.640296301846149,
            "z": 0.0
        },
        {
            "qw": 1.0,
            "qx": 0.0,
            "qy": 0.0,
            "qz": 0.0,
            "x": 0.8363915508447803,
            "y": 2.639656195635439,
            "z": 0.0
        },
        {
            "qw": 1.0,
            "qx": 0.0,
            "qy": 0.0,
            "qz": 0.0,
            "x": 0.8114068092615412,
            "y": 2.638784918766987,
            "z": 0.0
        },
        {
            "qw": 1.0,
            "qx": 0.0,
            "qy": 0.0,
            "qz": 0.0,
            "x": 0.7864243564966955,
            "y": 2.6378564214386984,
            "z": 0.0
        },
        {
            "qw": 1.0,
            "qx": 0.0,
            "qy": 0.0,
            "qz": 0.0,
            "x": 0.7614556366422107,
            "y": 2.6366067265958577,
            "z": 0.0
        },
        {
            "qw": 1.0,
            "qx": 0.0,
            "qy": 0.0,
            "qz": 0.0,
            "x": 0.7364899685455839,
            "y": 2.6352929448379996,
            "z": 0.0
        },
        {
            "qw": 1.0,
            "qx": 0.0,
            "qy": 0.0,
            "qz": 0.0,
            "x": 0.7115563439064658,
            "y": 2.63347638597304,
            "z": 0.0
        },
        {
            "qw": 1.0,
            "qx": 0.0,
            "qy": 0.0,
            "qz": 0.0,
            "x": 0.6866288227830637,
            "y": 2.6315698002512704,
            "z": 0.0
        },
        {
            "qw": 1.0,
            "qx": 0.0,
            "qy": 0.0,
            "qz": 0.0,
            "x": 0.6617821732428979,
            "y": 2.6288079593898033,
            "z": 0.0
        },
        {
            "qw": 1.0,
            "qx": 0.0,
            "qy": 0.0,
            "qz": 0.0,
            "x": 0.636950782492022,
            "y": 2.6259057376668693,
            "z": 0.0
        },
        {
            "qw": 1.0,
            "qx": 0.0,
            "qy": 0.0,
            "qz": 0.0,
            "x": 0.612856391263847,
            "y": 2.619239935565588,
            "z": 0.0
        },
        {
            "qw": 1.0,
            "qx": 0.0,
            "qy": 0.0,
            "qz": 0.0,
            "x": 0.5891259221602354,
            "y": 2.6113747926261226,
            "z": 0.0
        },
        {
            "qw": 1.0,
            "qx": 0.0,
            "qy": 0.0,
            "qz": 0.0,
            "x": 0.5644272828761814,
            "y": 2.607502874843817,
            "z": 0.0
        },
        {
            "qw": 1.0,
            "qx": 0.0,
            "qy": 0.0,
            "qz": 0.0,
            "x": 0.5397187253790889,
            "y": 2.6036988586738516,
            "z": 0.0
        },
        {
            "qw": 1.0,
            "qx": 0.0,
            "qy": 0.0,
            "qz": 0.0,
            "x": 0.5148194330158731,
            "y": 2.6014581054666337,
            "z": 0.0
        },
        {
            "qw": 1.0,
            "qx": 0.0,
            "qy": 0.0,
            "qz": 0.0,
            "x": 0.4898850454372905,
            "y": 2.59964765011739,
            "z": 0.0
        },
        {
            "qw": 1.0,
            "qx": 0.0,
            "qy": 0.0,
            "qz": 0.0,
            "x": 0.46551599600189775,
            "y": 2.605229315239626,
            "z": 0.0
        },
        {
            "qw": 1.0,
            "qx": 0.0,
            "qy": 0.0,
            "qz": 0.0,
            "x": 0.44086084426731986,
            "y": 2.609369787713433,
            "z": 0.0
        },
        {
            "qw": 1.0,
            "qx": 0.0,
            "qy": 0.0,
            "qz": 0.0,
            "x": 0.4160607340344882,
            "y": 2.6125230165201856,
            "z": 0.0
        },
        {
            "qw": 1.0,
            "qx": 0.0,
            "qy": 0.0,
            "qz": 0.0,
            "x": 0.39117555605136545,
            "y": 2.6149186464386958,
            "z": 0.0
        },
        {
            "qw": 1.0,
            "qx": 0.0,
            "qy": 0.0,
            "qz": 0.0,
            "x": 0.3662575716712695,
            "y": 2.6169427248379975,
            "z": 0.0
        },
        {
            "qw": 1.0,
            "qx": 0.0,
            "qy": 0.0,
            "qz": 0.0,
            "x": 0.3413147917585775,
            "y": 2.6186288210545285,
            "z": 0.0
        },
        {
            "qw": 1.0,
            "qx": 0.0,
            "qy": 0.0,
            "qz": 0.0,
            "x": 0.31637811536160143,
            "y": 2.620406470006799,
            "z": 0.0
        },
        {
            "qw": 1.0,
            "qx": 0.0,
            "qy": 0.0,
            "qz": 0.0,
            "x": 0.2914353354489094,
            "y": 2.6220979067995813,
            "z": 0.0
        },
        {
            "qw": 1.0,
            "qx": 0.0,
            "qy": 0.0,
            "qz": 0.0,
            "x": 0.26653909484355154,
            "y": 2.624376806980024,
            "z": 0.0
        },
        {
            "qw": 1.0,
            "qx": 0.0,
            "qy": 0.0,
            "qz": 0.0,
            "x": 0.24165773155775128,
            "y": 2.6268067691744363,
            "z": 0.0
        },
        {
            "qw": 1.0,
            "qx": 0.0,
            "qy": 0.0,
            "qz": 0.0,
            "x": 0.21716928209616526,
            "y": 2.631838354942772,
            "z": 0.0
        },
        {
            "qw": 1.0,
            "qx": 0.0,
            "qy": 0.0,
            "qz": 0.0,
            "x": 0.19296273876670966,
            "y": 2.63808759209644,
            "z": 0.0
        },
        {
            "qw": 1.0,
            "qx": 0.0,
            "qy": 0.0,
            "qz": 0.0,
            "x": 0.16935701026554284,
            "y": 2.646319708918327,
            "z": 0.0
        },
        {
            "qw": 1.0,
            "qx": 0.0,
            "qy": 0.0,
            "qz": 0.0,
            "x": 0.14661950687496983,
            "y": 2.6567117073641953,
            "z": 0.0
        },
        {
            "qw": 1.0,
            "qx": 0.0,
            "qy": 0.0,
            "qz": 0.0,
            "x": 0.12229966703503692,
            "y": 2.662504706718096,
            "z": 0.0
        },
        {
            "qw": 1.0,
            "qx": 0.0,
            "qy": 0.0,
            "qz": 0.0,
            "x": 0.09765710380162318,
            "y": 2.6667168955015654,
            "z": 0.0
        },
        {
            "qw": 1.0,
            "qx": 0.0,
            "qy": 0.0,
            "qz": 0.0,
            "x": 0.07298631180802317,
            "y": 2.6707597117239175,
            "z": 0.0
        },
        {
            "qw": 1.0,
            "qx": 0.0,
            "qy": 0.0,
            "qz": 0.0,
            "x": 0.04825257730860244,
            "y": 2.6743989329695523,
            "z": 0.0
        },
        {
            "qw": 1.0,
            "qx": 0.0,
            "qy": 0.0,
            "qz": 0.0,
            "x": 0.023656934852255063,
            "y": 2.6788773876261303,
            "z": 0.0
        },
        {
            "qw": 1.0,
            "qx": 0.0,
            "qy": 0.0,
            "qz": 0.0,
            "x": -0.0008605063089817122,
            "y": 2.683766303714606,
            "z": 0.0
        },
        {
            "qw": 1.0,
            "qx": 0.0,
            "qy": 0.0,
            "qz": 0.0,
            "x": -0.024920183791522277,
            "y": 2.6905579908275286,
            "z": 0.0
        },
        {
            "qw": 1.0,
            "qx": 0.0,
            "qy": 0.0,
            "qz": 0.0,
            "x": -0.04853201580840505,
            "y": 2.6987733229811965,
            "z": 0.0
        },
        {
            "qw": 1.0,
            "qx": 0.0,
            "qy": 0.0,
            "qz": 0.0,
            "x": -0.07147780167278484,
            "y": 2.7086976395353304,
            "z": 0.0
        },
        {
            "qw": 1.0,
            "qx": 0.0,
            "qy": 0.0,
            "qz": 0.0,
            "x": -0.09388762256335781,
            "y": 2.719777809378172,
            "z": 0.0
        },
        {
            "qw": 1.0,
            "qx": 0.0,
            "qy": 0.0,
            "qz": 0.0,
            "x": -0.11646872336370961,
            "y": 2.7305062641278823,
            "z": 0.0
        },
        {
            "qw": 1.0,
            "qx": 0.0,
            "qy": 0.0,
            "qz": 0.0,
            "x": -0.13965979426592412,
            "y": 2.7398438802338205,
            "z": 0.0
        },
        {
            "qw": 1.0,
            "qx": 0.0,
            "qy": 0.0,
            "qz": 0.0,
            "x": -0.16239004973158444,
            "y": 2.7502519004084434,
            "z": 0.0
        },
        {
            "qw": 1.0,
            "qx": 0.0,
            "qy": 0.0,
            "qz": 0.0,
            "x": -0.1836066332996893,
            "y": 2.7634759301465124,
            "z": 0.0
        },
        {
            "qw": 1.0,
            "qx": 0.0,
            "qy": 0.0,
            "qz": 0.0,
            "x": -0.20509863801447636,
            "y": 2.7762460109032077,
            "z": 0.0
        },
        {
            "qw": 1.0,
            "qx": 0.0,
            "qy": 0.0,
            "qz": 0.0,
            "x": -0.22734747867804117,
            "y": 2.7876473782606013,
            "z": 0.0
        },
        {
            "qw": 1.0,
            "qx": 0.0,
            "qy": 0.0,
            "qz": 0.0,
            "x": -0.24910346044754306,
            "y": 2.7999627470964583,
            "z": 0.0
        },
        {
            "qw": 1.0,
            "qx": 0.0,
            "qy": 0.0,
            "qz": 0.0,
            "x": -0.27003470465592727,
            "y": 2.813633096421256,
            "z": 0.0
        },
        {
            "qw": 1.0,
            "qx": 0.0,
            "qy": 0.0,
            "qz": 0.0,
            "x": -0.2902186496588399,
            "y": 2.828385293906706,
            "z": 0.0
        },
        {
            "qw": 1.0,
            "qx": 0.0,
            "qy": 0.0,
            "qz": 0.0,
            "x": -0.31055632696384805,
            "y": 2.8429238683420976,
            "z": 0.0
        },
        {
            "qw": 1.0,
            "qx": 0.0,
            "qy": 0.0,
            "qz": 0.0,
            "x": -0.32894087923975235,
            "y": 2.8598657020906444,
            "z": 0.0
        },
        {
            "qw": 1.0,
            "qx": 0.0,
            "qy": 0.0,
            "qz": 0.0,
            "x": -0.3467345349004063,
            "y": 2.8774262797448955,
            "z": 0.0
        },
        {
            "qw": 1.0,
            "qx": 0.0,
            "qy": 0.0,
            "qz": 0.0,
            "x": -0.36533385463556556,
            "y": 2.894131602259449,
            "z": 0.0
        },
        {
            "qw": 1.0,
            "qx": 0.0,
            "qy": 0.0,
            "qz": 0.0,
            "x": -0.38197394582590505,
            "y": 2.9127892868636422,
            "z": 0.0
        },
        {
            "qw": 1.0,
            "qx": 0.0,
            "qy": 0.0,
            "qz": 0.0,
            "x": -0.3984889149440676,
            "y": 2.931557597690187,
            "z": 0.0
        },
        {
            "qw": 1.0,
            "qx": 0.0,
            "qy": 0.0,
            "qz": 0.0,
            "x": -0.41631690288062373,
            "y": 2.9490838430685358,
            "z": 0.0
        },
        {
            "qw": 1.0,
            "qx": 0.0,
            "qy": 0.0,
            "qz": 0.0,
            "x": -0.4310317163323134,
            "y": 2.9692941094829735,
            "z": 0.0
        },
        {
            "qw": 1.0,
            "qx": 0.0,
            "qy": 0.0,
            "qz": 0.0,
            "x": -0.4462065822810928,
            "y": 2.9891618160778535,
            "z": 0.0
        },
        {
            "qw": 1.0,
            "qx": 0.0,
            "qy": 0.0,
            "qz": 0.0,
            "x": -0.46290122364314357,
            "y": 3.007770672556319,
            "z": 0.0
        },
        {
            "qw": 1.0,
            "qx": 0.0,
            "qy": 0.0,
            "qz": 0.0,
            "x": -0.4768355500226562,
            "y": 3.028527203627334,
            "z": 0.0
        },
        {
            "qw": 1.0,
            "qx": 0.0,
            "qy": 0.0,
            "qz": 0.0,
            "x": -0.49170409577644136,
            "y": 3.048625317940491,
            "z": 0.0
        },
        {
            "qw": 1.0,
            "qx": 0.0,
            "qy": 0.0,
            "qz": 0.0,
            "x": -0.5086135045977471,
            "y": 3.0670396248555107,
            "z": 0.0
        },
        {
            "qw": 1.0,
            "qx": 0.0,
            "qy": 0.0,
            "qz": 0.0,
            "x": -0.5215304512013574,
            "y": 3.088443891531881,
            "z": 0.0
        },
        {
            "qw": 1.0,
            "qx": 0.0,
            "qy": 0.0,
            "qz": 0.0,
            "x": -0.5356806894493218,
            "y": 3.1090539382257134,
            "z": 0.0
        },
        {
            "qw": 1.0,
            "qx": 0.0,
            "qy": 0.0,
            "qz": 0.0,
            "x": -0.5514022015244109,
            "y": 3.128491346962619,
            "z": 0.0
        },
        {
            "qw": 1.0,
            "qx": 0.0,
            "qy": 0.0,
            "qz": 0.0,
            "x": -0.5612979078486262,
            "y": 3.151449721328163,
            "z": 0.0
        },
        {
            "qw": 1.0,
            "qx": 0.0,
            "qy": 0.0,
            "qz": 0.0,
            "x": -0.5714217330727251,
            "y": 3.174308150623858,
            "z": 0.0
        },
        {
            "qw": 1.0,
            "qx": 0.0,
            "qy": 0.0,
            "qz": 0.0,
            "x": -0.5835200456309337,
            "y": 3.196186202707679,
            "z": 0.0
        },
        {
            "qw": 1.0,
            "qx": 0.0,
            "qy": 0.0,
            "qz": 0.0,
            "x": -0.598861613852705,
            "y": 3.2159249725330596,
            "z": 0.0
        },
        {
            "qw": 1.0,
            "qx": 0.0,
            "qy": 0.0,
            "qz": 0.0,
            "x": -0.6151141317950817,
            "y": 3.234921402259488,
            "z": 0.0
        },
        {
            "qw": 1.0,
            "qx": 0.0,
            "qy": 0.0,
            "qz": 0.0,
            "x": -0.6146239431891445,
            "y": 3.2599160620557655,
            "z": 0.0
        },
        {
            "qw": 1.0,
            "qx": 0.0,
            "qy": 0.0,
            "qz": 0.0,
            "x": -0.6153266104359432,
            "y": 3.284906144215256,
            "z": 0.0
        },
        {
            "qw": 1.0,
            "qx": 0.0,
            "qy": 0.0,
            "qz": 0.0,
            "x": -0.6174208792659783,
            "y": 3.3098184065493683,
            "z": 0.0
        },
        {
            "qw": 1.0,
            "qx": 0.0,
            "qy": 0.0,
            "qz": 0.0,
            "x": -0.6193034323946165,
            "y": 3.3347474535516994,
            "z": 0.0
        },
        {
            "qw": 1.0,
            "qx": 0.0,
            "qy": 0.0,
            "qz": 0.0,
            "x": -0.6182330283259319,
            "y": 3.3597245657402937,
            "z": 0.0
        },
        {
            "qw": 1.0,
            "qx": 0.0,
            "qy": 0.0,
            "qz": 0.0,
            "x": -0.6141989859074215,
            "y": 3.384397265082555,
            "z": 0.0
        },
        {
            "qw": 1.0,
            "qx": 0.0,
            "qy": 0.0,
            "qz": 0.0,
            "x": -0.6073466451070715,
            "y": 3.4084397764271444,
            "z": 0.0
        },
        {
            "qw": 1.0,
            "qx": 0.0,
            "qy": 0.0,
            "qz": 0.0,
            "x": -0.597919002144323,
            "y": 3.431594226235063,
            "z": 0.0
        },
        {
            "qw": 1.0,
            "qx": 0.0,
            "qy": 0.0,
            "qz": 0.0,
            "x": -0.5862425951099794,
            "y": 3.453699634279303,
            "z": 0.0
        },
        {
            "qw": 1.0,
            "qx": 0.0,
            "qy": 0.0,
            "qz": 0.0,
            "x": -0.5726580764749372,
            "y": 3.4746865730685954,
            "z": 0.0
        },
        {
            "qw": 1.0,
            "qx": 0.0,
            "qy": 0.0,
            "qz": 0.0,
            "x": -0.5573096417979855,
            "y": 3.494420765257189,
            "z": 0.0
        },
        {
            "qw": 1.0,
            "qx": 0.0,
            "qy": 0.0,
            "qz": 0.0,
            "x": -0.54093848676888,
            "y": 3.5133141981559106,
            "z": 0.0
        },
        {
            "qw": 1.0,
            "qx": 0.0,
            "qy": 0.0,
            "qz": 0.0,
            "x": -0.5234336036955369,
            "y": 3.5311631669277403,
            "z": 0.0
        },
        {
            "qw": 1.0,
            "qx": 0.0,
            "qy": 0.0,
            "qz": 0.0,
            "x": -0.5048392430668969,
            "y": 3.5478738300185455,
            "z": 0.0
        },
        {
            "qw": 1.0,
            "qx": 0.0,
            "qy": 0.0,
            "qz": 0.0,
            "x": -0.485619272077372,
            "y": 3.5638612264970106,
            "z": 0.0
        },
        {
            "qw": 1.0,
            "qx": 0.0,
            "qy": 0.0,
            "qz": 0.0,
            "x": -0.464179910185635,
            "y": 3.5767205711710517,
            "z": 0.0
        },
        {
            "qw": 1.0,
            "qx": 0.0,
            "qy": 0.0,
            "qz": 0.0,
            "x": -0.4408980494871457,
            "y": 3.5858285424981773,
            "z": 0.0
        },
        {
            "qw": 1.0,
            "qx": 0.0,
            "qy": 0.0,
            "qz": 0.0,
            "x": -0.3999999165534973,
            "y": 3.6000001430511475,
            "z": 0.0
        }
    ],
    "start_position": [
        -0.3976743532689646,
        3.634996046826289,
        0.0
    ]
}