{
    "cost": 9.221360984626822,
    "frame_id": "/map",
    "goal_position": [
        0.5099371298355253,
        -4.599948797331296,
        0.0
    ],
    "path": [
        {
            "qw": 1.0,
            "qx": 0.0,
            "qy": 0.0,
            "qz": 0.0,
            "x": 0.5099371298355253,
            "y": -4.599948797331296,
            "z": 0.0
        },
        {
            "qw": 1.0,
            "qx": 0.0,
            "qy": 0.0,
            "qz": 0.0,
            "x": 0.5000000968575478,
            "y": -4.599999979138374,
            "z": 0.0
        },
        {
            "qw": 1.0,
            "qx": 0.0,
            "qy": 0.0,
            "qz": 0.0,
            "x": 0.5500000976026058,
            "y": -4.549999978393316,
            "z": 0.0
        },
        {
            "qw": 1.0,
            "qx": 0.0,
            "qy": 0.0,
            "qz": 0.0,
            "x": 0.5544571899541779,
            "y": -4.525400521239646,
            "z": 0.0
        },
        {
            "qw": 1.0,
            "qx": 0.0,
            "qy": 0.0,
            "qz": 0.0,
            "x": 0.5587128662871237,
            "y": -4.5007653966660115,
            "z": 0.0
        },
        {
            "qw": 1.0,
            "qx": 0.0,
            "qy": 0.0,
            "qz": 0.0,
            "x": 0.562603094616577,
            "y": -4.4760699045072485,
            "z": 0.0
        },
        {
            "qw": 1.0,
            "qx": 0.0,
            "qy": 0.0,
            "qz": 0.0,
            "x": 0.5665566469215833,
            "y": -4.45138452129639,
            "z": 0.0
        },
        {
            "qw": 1.0,
            "qx": 0.0,
            "qy": 0.0,
            "qz": 0.0,
            "x": 0.5702454592324102,
            "y": -4.426658130089315,
            "z": 0.0
        },
        {
            "qw": 1.0,
            "qx": 0.0,
            "qy": 0.0,
            "qz": 0.0,
            "x": 0.5723137881206526,
            "y": -4.4017438650391085,
            "z": 0.0
        },
        {
            "qw": 1.0,
            "qx": 0.0,
            "qy": 0.0,
            "qz": 0.0,
            "x": 0.5732361819332255,
            "y": -4.3767608400696645,
            "z": 0.0
        },
        {
            "qw": 1.0,
            "qx": 0.0,
            "qy": 0.0,
            "qz": 0.0,
            "x": 0.5733231570321777,
            "y": -4.351761030432002,
            "z": 0.0
        },
        {
            "qw": 1.0,
            "qx": 0.0,
            "qy": 0.0,
            "qz": 0.0,
            "x": 0.5728859927190229,
            "y": -4.326764844756795,
            "z": 0.0
        },
        {
            "qw": 1.0,
            "qx": 0.0,
            "qy": 0.0,
            "qz": 0.0,
            "x": 0.5719750429984174,
            "y": -4.301781438317619,
            "z": 0.0
        },
        {
            "qw": 1.0,
            "qx": 0.0,
            "qy": 0.0,
            "qz": 0.0,
            "x": 0.5707894350705942,
            "y": -4.276809666705276,
            "z": 0.0
        },
        {
            "qw": 1.0,
            "qx": 0.0,
            "qy": 0.0,
            "qz": 0.0,
            "x": 0.569186499255693,
            "y": -4.251860974011734,
            "z": 0.0
        },
        {
            "qw": 1.0,
            "qx": 0.0,
            "qy": 0.0,
            "qz": 0.0,
            "x": 0.567369177451269,
            "y": -4.22692715863775,
            "z": 0.0
        },
        {
            "qw": 1.0,
            "qx": 0.0,
            "qy": 0.0,
            "qz": 0.0,
            "x": 0.5649811769274038,
            "y": -4.202041599184895,
            "z": 0.0
        },
        {
            "qw": 1.0,
            "qx": 0.0,
            "qy": 0.0,
            "qz": 0.0,
            "x": 0.5623322511066817,
            "y": -4.177182170408699,
            "z": 0.0
        },
        {
            "qw": 1.0,
            "qx": 0.0,
            "qy": 0.0,
            "qz": 0.0,
            "x": 0.5591828369972518,
            "y": -4.152381487971269,
            "z": 0.0
        },
        {
            "qw": 1.0,
            "qx": 0.0,
            "qy": 0.0,
            "qz": 0.0,
            "x": 0.555655004913433,
            "y": -4.127631541008228,
            "z": 0.0
        },
        {
            "qw": 1.0,
            "qx": 0.0,
            "qy": 0.0,
            "qz": 0.0,
            "x": 0.5497368834873555,
            "y": -4.103342218746874,
            "z": 0.0
        },
        {
            "qw": 1.0,
            "qx": 0.0,
            "qy": 0.0,
            "qz": 0.0,
            "x": 0.5414696714501019,
            "y": -4.0797486972771395,
            "z": 0.0
        },
        {
            "qw": 1.0,
            "qx": 0.0,
            "qy": 0.0,
            "qz": 0.0,
            "x": 0.5324875851346178,
            "y": -4.056418008452923,
            "z": 0.0
        },
        {
            "qw": 1.0,
            "qx": 0.0,
            "qy": 0.0,
            "qz": 0.0,
            "x": 0.5221932429402045,
            "y": -4.033635682368811,
            "z": 0.0
        },
        {
            "qw": 1.0,
            "qx": 0.0,
            "qy": 0.0,
            "qz": 0.0,
            "x": 0.5112900750531253,
            "y": -4.011138695644419,
            "z": 0.0
        },
        {
            "qw": 1.0,
            "qx": 0.0,
            "qy": 0.0,
            "qz": 0.0,
            "x": 0.4998002067178504,
            "y": -3.988935249878992,
            "z": 0.0
        },
        {
            "qw": 1.0,
            "qx": 0.0,
            "qy": 0.0,
            "qz": 0.0,
            "x": 0.5003083244012032,
            "y": -3.963940399347848,
            "z": 0.0
        },
        {
            "qw": 1.0,
            "qx": 0.0,
            "qy": 0.0,
            "qz": 0.0,
            "x": 0.500513555117152,
            "y": -3.9389411619147836,
            "z": 0.0
        },
        {
            "qw": 1.0,
            "qx": 0.0,
            "qy": 0.0,
            "qz": 0.0,
            "x": 0.5005051627830426,
            "y": -3.9139411615422546,
            "z": 0.0
        },
        {
            "qw": 1.0,
            "qx": 0.0,
            "qy": 0.0,
            "qz": 0.0,
            "x": 0.5003457084349634,
            "y": -3.888941733374324,
            "z": 0.0
        },
        {
            "qw": 1.0,
            "qx": 0.0,
            "qy": 0.0,
            "qz": 0.0,
            "x": 0.5000779166829261,
            "y": -3.863943258880724,
            "z": 0.0
        },
        {
            "qw": 1.0,
            "qx": 0.0,
            "qy": 0.0,
            "qz": 0.0,
            "x": 0.49972391277140105,
            "y": -3.8389457380614544,
            "z": 0.0
        },
        {
            "qw": 1.0,
            "qx": 0.0,
            "qy": 0.0,
            "qz": 0.0,
            "x": 0.49932260661307737,
            "y": -3.8139489801816495,
            "z": 0.0
        },
        {
            "qw": 1.0,
            "qx": 0.0,
            "qy": 0.0,
            "qz": 0.0,
            "x": 0.4989197745758247,
            "y": -3.7889522223018446,
            "z": 0.0
        },
        {
            "qw": 1.0,
            "qx": 0.0,
            "qy": 0.0,
            "qz": 0.0,
            "x": 0.498462773836593,
            "y": -3.7639564180963703,
            "z": 0.0
        },
        {
            "qw": 1.0,
            "qx": 0.0,
            "qy": 0.0,
            "qz": 0.0,
            "x": 0.4978798880857198,
            "y": -3.7389630934441556,
            "z": 0.0
        },
        {
            "qw": 1.0,
            "qx": 0.0,
            "qy": 0.0,
            "qz": 0.0,
            "x": 0.497254277724835,
            "y": -3.7139709132011376,
            "z": 0.0
        },
        {
            "qw": 1.0,
            "qx": 0.0,
            "qy": 0.0,
            "qz": 0.0,
            "x": 0.49668970252110967,
            "y": -3.6889773978140568,
            "z": 0.0
        },
        {
            "qw": 1.0,
            "qx": 0.0,
            "qy": 0.0,
            "qz": 0.0,
            "x": 0.49616174841168004,
            "y": -3.6639829287526453,
            "z": 0.0
        },
        {
            "qw": 1.0,
            "qx": 0.0,
            "qy": 0.0,
            "qz": 0.0,
            "x": 0.4956490530915403,
            "y": -3.6389880782215016,
            "z": 0.0
        },
        {
            "qw": 1.0,
            "qx": 0.0,
            "qy": 0.0,
            "qz": 0.0,
            "x": 0.4951783194419477,
            "y": -3.6139926554857595,
            "z": 0.0
        },
        {
            "qw": 1.0,
            "qx": 0.0,
            "qy": 0.0,
            "qz": 0.0,
            "x": 0.4947747244652305,
            "y": -3.5889958976059546,
            "z": 0.0
        },
        {
            "qw": 1.0,
            "qx": 0.0,
            "qy": 0.0,
            "qz": 0.0,
            "x": 0.49445963046639463,
            "y": -3.563997804582087,
            "z": 0.0
        },
        {
            "qw": 1.0,
            "qx": 0.0,
            "qy": 0.0,
            "qz": 0.0,
            "x": 0.4942566885688393,
            "y": -3.5389987578838884,
            "z": 0.0
        },
        {
            "qw": 1.0,
            "qx": 0.0,
            "qy": 0.0,
            "qz": 0.0,
            "x": 0.49417963168292545,
            "y": -3.5139987575113594,
            "z": 0.0
        },
        {
            "qw": 1.0,
            "qx": 0.0,
            "qy": 0.0,
            "qz": 0.0,
            "x": 0.49424905917419437,
            "y": -3.4889989478736965,
            "z": 0.0
        },
        {
            "qw": 1.0,
            "qx": 0.0,
            "qy": 0.0,
            "qz": 0.0,
            "x": 0.4944283499483504,
            "y": -3.463999519705766,
            "z": 0.0
        },
        {
            "qw": 1.0,
            "qx": 0.0,
            "qy": 0.0,
            "qz": 0.0,
            "x": 0.49468698642681375,
            "y": -3.4390008544772996,
            "z": 0.0
        },
        {
            "qw": 1.0,
            "qx": 0.0,
            "qy": 0.0,
            "qz": 0.0,
            "x": 0.4949326529343807,
            "y": -3.4140019985139674,
            "z": 0.0
        },
        {
            "qw": 1.0,
            "qx": 0.0,
            "qy": 0.0,
            "qz": 0.0,
            "x": 0.49507684849317,
            "y": -3.3890025703460367,
            "z": 0.0
        },
        {
            "qw": 1.0,
            "qx": 0.0,
            "qy": 0.0,
            "qz": 0.0,
            "x": 0.49497461460492787,
            "y": -3.364002760708374,
            "z": 0.0
        },
        {
            "qw": 1.0,
            "qx": 0.0,
            "qy": 0.0,
            "qz": 0.0,
            "x": 0.49448251865032944,
            "y": -3.339007528707498,
            "z": 0.0
        },
        {
            "qw": 1.0,
            "qx": 0.0,
            "qy": 0.0,
            "qz": 0.0,
            "x": 0.49366998812064367,
            "y": -3.3140206890407313,
            "z": 0.0
        },
        {
            "qw": 1.0,
            "qx": 0.0,
            "qy": 0.0,
            "qz": 0.0,
            "x": 0.49254694122890896,
            "y": -3.2890458656705306,
            "z": 0.0
        },
        {
            "qw": 1.0,
            "qx": 0.0,
            "qy": 0.0,
            "qz": 0.0,
            "x": 0.4909447683534722,
            "y": -3.264097363711855,
            "z": 0.0
        },
        {
            "qw": 1.0,
            "qx": 0.0,
            "qy": 0.0,
            "qz": 0.0,
            "x": 0.4885895742265802,
            "y": -3.239208561766276,
            "z": 0.0
        },
        {
            "qw": 1.0,
            "qx": 0.0,
            "qy": 0.0,
            "qz": 0.0,
            "x": 0.48619623312646354,
            "y": -3.214323383783153,
            "z": 0.0
        },
        {
            "qw": 1.0,
            "qx": 0.0,
            "qy": 0.0,
            "qz": 0.0,
            "x": 0.4846306813453225,
            "y": -3.1893724022712178,
            "z": 0.0
        },
        {
            "qw": 1.0,
            "qx": 0.0,
            "qy": 0.0,
            "qz": 0.0,
            "x": 0.4850998891159861,
            "y": -3.1643767888006096,
            "z": 0.0
        },
        {
            "qw": 1.0,
            "qx": 0.0,
            "qy": 0.0,
            "qz": 0.0,
            "x": 0.4891709340985244,
            "y": -3.1397105744437965,
            "z": 0.0
        },
        {
            "qw": 1.0,
            "qx": 0.0,
            "qy": 0.0,
            "qz": 0.0,
            "x": 0.4943398489704691,
            "y": -3.115250544477263,
            "z": 0.0
        },
        {
            "qw": 1.0,
            "qx": 0.0,
            "qy": 0.0,
            "qz": 0.0,
            "x": 0.4984147086503299,
            "y": -3.0905850930599144,
            "z": 0.0
        },
        {
            "qw": 1.0,
            "qx": 0.0,
            "qy": 0.0,
            "qz": 0.0,
            "x": 0.5018776908796667,
            "y": -3.065825990823299,
            "z": 0.0
        },
        {
            "qw": 1.0,
            "qx": 0.0,
            "qy": 0.0,
            "qz": 0.0,
            "x": 0.5051545158796671,
            "y": -3.0410417115843558,
            "z": 0.0
        },
        {
            "qw": 1.0,
            "qx": 0.0,
            "qy": 0.0,
            "qz": 0.0,
            "x": 0.5085259453732647,
            "y": -3.0162700208465765,
            "z": 0.0
        },
        {
            "qw": 1.0,
            "qx": 0.0,
            "qy": 0.0,
            "qz": 0.0,
            "x": 0.5119050042615072,
            "y": -2.991499474517994,
            "z": 0.0
        },
        {
            "qw": 1.0,
            "qx": 0.0,
            "qy": 0.0,
            "qz": 0.0,
            "x": 0.5152932184233237,
            "y": -2.966730072598608,
            "z": 0.0
        },
        {
            "qw": 1.0,
            "qx": 0.0,
            "qy": 0.0,
            "qz": 0.0,
            "x": 0.518692113737643,
            "y": -2.9419621965581513,
            "z": 0.0
        },
        {
            "qw": 1.0,
            "qx": 0.0,
            "qy": 0.0,
            "qz": 0.0,
            "x": 0.5221009272650008,
            "y": -2.9171956556617573,
            "z": 0.0
        },
        {
            "qw": 1.0,
            "qx": 0.0,
            "qy": 0.0,
            "qz": 0.0,
            "x": 0.525513555489681,
            "y": -2.8924296869699617,
            "z": 0.0
        },
        {
            "qw": 1.0,
            "qx": 0.0,
            "qy": 0.0,
            "qz": 0.0,
            "x": 0.5289292354722193,
            "y": -2.8676640997478984,
            "z": 0.0
        },
        {
            "qw": 1.0,
            "qx": 0.0,
            "qy": 0.0,
            "qz": 0.0,
            "x": 0.532347204273151,
            "y": -2.8428990847304334,
            "z": 0.0
        },
        {
            "qw": 1.0,
            "qx": 0.0,
            "qy": 0.0,
            "qz": 0.0,
            "x": 0.5357689877714051,
            "y": -2.8181342604478345,
            "z": 0.0
        },
        {
            "qw": 1.0,
            "qx": 0.0,
            "qy": 0.0,
            "qz": 0.0,
            "x": 0.5391930600880528,
            "y": -2.793369626900102,
            "z": 0.0
        },
        {
            "qw": 1.0,
            "qx": 0.0,
            "qy": 0.0,
            "qz": 0.0,
            "x": 0.5426194212230939,
            "y": -2.7686057562918336,
            "z": 0.0
        },
        {
            "qw": 1.0,
            "qx": 0.0,
            "qy": 0.0,
            "qz": 0.0,
            "x": 0.546048834115993,
            "y": -2.7438418856835654,
            "z": 0.0
        },
        {
            "qw": 1.0,
            "qx": 0.0,
            "qy": 0.0,
            "qz": 0.0,
            "x": 0.5494805358272856,
            "y": -2.7190787780147616,
            "z": 0.0
        },
        {
            "qw": 1.0,
            "qx": 0.0,
            "qy": 0.0,
            "qz": 0.0,
            "x": 0.5529152892964362,
            "y": -2.694315670345958,
            "z": 0.0
        },
        {
            "qw": 1.0,
            "qx": 0.0,
            "qy": 0.0,
            "qz": 0.0,
            "x": 0.5563523315839802,
            "y": -2.6695533256166186,
            "z": 0.0
        },
        {
            "qw": 1.0,
            "qx": 0.0,
            "qy": 0.0,
            "qz": 0.0,
            "x": 0.5597939515083112,
            "y": -2.6447913623570116,
            "z": 0.0
        },
        {
            "qw": 1.0,
            "qx": 0.0,
            "qy": 0.0,
            "qz": 0.0,
            "x": 0.5632370973115712,
            "y": -2.6200293990974046,
            "z": 0.0
        },
        {
            "qw": 1.0,
            "qx": 0.0,
            "qy": 0.0,
            "qz": 0.0,
            "x": 0.5666840578121537,
            "y": -2.595268198777262,
            "z": 0.0
        },
        {
            "qw": 1.0,
            "qx": 0.0,
            "qy": 0.0,
            "qz": 0.0,
            "x": 0.5701340700705941,
            "y": -2.570507379926852,
            "z": 0.0
        },
        {
            "qw": 1.0,
            "qx": 0.0,
            "qy": 0.0,
            "qz": 0.0,
            "x": 0.5735856082079636,
            "y": -2.545746942546174,
            "z": 0.0
        },
        {
            "qw": 1.0,
            "qx": 0.0,
            "qy": 0.0,
            "qz": 0.0,
            "x": 0.577040198103191,
            "y": -2.520986505165496,
            "z": 0.0
        },
        {
            "qw": 1.0,
            "qx": 0.0,
            "qy": 0.0,
            "qz": 0.0,
            "x": 0.5804978397562763,
            "y": -2.4962268307242823,
            "z": 0.0
        },
        {
            "qw": 1.0,
            "qx": 0.0,
            "qy": 0.0,
            "qz": 0.0,
            "x": 0.5839570072882907,
            "y": -2.471467537752801,
            "z": 0.0
        },
        {
            "qw": 1.0,
            "qx": 0.0,
            "qy": 0.0,
            "qz": 0.0,
            "x": 0.587419226578163,
            "y": -2.4467082447813198,
            "z": 0.0
        },
        {
            "qw": 1.0,
            "qx": 0.0,
            "qy": 0.0,
            "qz": 0.0,
            "x": 0.5908829717469644,
            "y": -2.4219493332795707,
            "z": 0.0
        },
        {
            "qw": 1.0,
            "qx": 0.0,
            "qy": 0.0,
            "qz": 0.0,
            "x": 0.5943497686736237,
            "y": -2.397190803247554,
            "z": 0.0
        },
        {
            "qw": 1.0,
            "qx": 0.0,
            "qy": 0.0,
            "qz": 0.0,
            "x": 0.5978188544186764,
            "y": -2.3724326546852694,
            "z": 0.0
        },
        {
            "qw": 1.0,
            "qx": 0.0,
            "qy": 0.0,
            "qz": 0.0,
            "x": 0.6012909919215872,
            "y": -2.347674887592717,
            "z": 0.0
        },
        {
            "qw": 1.0,
            "qx": 0.0,
            "qy": 0.0,
            "qz": 0.0,
            "x": 0.6047646553034269,
            "y": -2.322917501969897,
            "z": 0.0
        },
        {
            "qw": 1.0,
            "qx": 0.0,
            "qy": 0.0,
            "qz": 0.0,
            "x": 0.6082421333825891,
            "y": -2.2981604978168093,
            "z": 0.0
        },
        {
            "qw": 1.0,
            "qx": 0.0,
            "qy": 0.0,
            "qz": 0.0,
            "x": 0.6117219002801448,
            "y": -2.2734038751334538,
            "z": 0.0
        },
        {
            "qw": 1.0,
            "qx": 0.0,
            "qy": 0.0,
            "qz": 0.0,
            "x": 0.6152047189355585,
            "y": -2.2486476339198305,
            "z": 0.0
        },
        {
            "qw": 1.0,
            "qx": 0.0,
            "qy": 0.0,
            "qz": 0.0,
            "x": 0.6186890634699012,
            "y": -2.2238917741759394,
            "z": 0.0
        },
        {
            "qw": 1.0,
            "qx": 0.0,
            "qy": 0.0,
            "qz": 0.0,
            "x": 0.6221764597621018,
            "y": -2.1991362959017806,
            "z": 0.0
        },
        {
            "qw": 1.0,
            "qx": 0.0,
            "qy": 0.0,
            "qz": 0.0,
            "x": 0.6256646189937669,
            "y": -2.174380817627622,
            "z": 0.0
        },
        {
            "qw": 1.0,
            "qx": 0.0,
            "qy": 0.0,
            "qz": 0.0,
            "x": 0.62915582998329,
            "y": -2.1496257208231953,
            "z": 0.0
        },
        {
            "qw": 1.0,
            "qx": 0.0,
            "qy": 0.0,
            "qz": 0.0,
            "x": 0.6326485668517421,
            "y": -2.124871005488501,
            "z": 0.0
        },
        {
            "qw": 1.0,
            "qx": 0.0,
            "qy": 0.0,
            "qz": 0.0,
            "x": 0.6361428295991232,
            "y": -2.1001162901538066,
            "z": 0.0
        },
        {
            "qw": 1.0,
            "qx": 0.0,
            "qy": 0.0,
            "qz": 0.0,
            "x": 0.6396393811648977,
            "y": -2.0753619562888446,
            "z": 0.0
        },
        {
            "qw": 1.0,
            "qx": 0.0,
            "qy": 0.0,
            "qz": 0.0,
            "x": 0.6431374586096013,
            "y": -2.0506080038936148,
            "z": 0.0
        },
        {
            "qw": 1.0,
            "qx": 0.0,
            "qy": 0.0,
            "qz": 0.0,
            "x": 0.6466378248726983,
            "y": -2.025854051498385,
            "z": 0.0
        },
        {
            "qw": 1.0,
            "qx": 0.0,
            "qy": 0.0,
            "qz": 0.0,
            "x": 0.6501397170147243,
            "y": -2.0011008620426196,
            "z": 0.0
        },
        {
            "qw": 1.0,
            "qx": 0.0,
            "qy": 0.0,
            "qz": 0.0,
            "x": 0.6536438979751438,
            "y": -1.9763476725868543,
            "z": 0.0
        },
        {
            "qw": 1.0,
            "qx": 0.0,
            "qy": 0.0,
            "qz": 0.0,
            "x": 0.6571518936328857,
            "y": -1.9515948646008212,
            "z": 0.0
        },
        {
            "qw": 1.0,
            "qx": 0.0,
            "qy": 0.0,
            "qz": 0.0,
            "x": 0.6606598892906277,
            "y": -1.9268420566147881,
            "z": 0.0
        },
        {
            "qw": 1.0,
            "qx": 0.0,
            "qy": 0.0,
            "qz": 0.0,
            "x": 0.6641709367062276,
            "y": -1.9020900115682196,
            "z": 0.0
        },
        {
            "qw": 1.0,
            "qx": 0.0,
            "qy": 0.0,
            "qz": 0.0,
            "x": 0.667682747061292,
            "y": -1.877337966521651,
            "z": 0.0
        },
        {
            "qw": 1.0,
            "qx": 0.0,
            "qy": 0.0,
            "qz": 0.0,
            "x": 0.6711960832952855,
            "y": -1.8525859214750824,
            "z": 0.0
        },
        {
            "qw": 1.0,
            "qx": 0.0,
            "qy": 0.0,
            "qz": 0.0,
            "x": 0.6747101824687434,
            "y": -1.827834257898246,
            "z": 0.0
        },
        {
            "qw": 1.0,
            "qx": 0.0,
            "qy": 0.0,
            "qz": 0.0,
            "x": 0.6782250445816658,
            "y": -1.8030825943214097,
            "z": 0.0
        },
        {
            "qw": 1.0,
            "qx": 0.0,
            "qy": 0.0,
            "qz": 0.0,
            "x": 0.6817399066945882,
            "y": -1.7783309307445734,
            "z": 0.0
        },
        {
            "qw": 1.0,
            "qx": 0.0,
            "qy": 0.0,
            "qz": 0.0,
            "x": 0.6852562946864396,
            "y": -1.753579267167737,
            "z": 0.0
        },
        {
            "qw": 1.0,
            "qx": 0.0,
            "qy": 0.0,
            "qz": 0.0,
            "x": 0.688772682678291,
            "y": -1.728827985060633,
            "z": 0.0
        },
        {
            "qw": 1.0,
            "qx": 0.0,
            "qy": 0.0,
            "qz": 0.0,
            "x": 0.6922905965490713,
            "y": -1.7040767029535289,
            "z": 0.0
        },
        {
            "qw": 1.0,
            "qx": 0.0,
            "qy": 0.0,
            "qz": 0.0,
            "x": 0.6958085104198517,
            "y": -1.6793254208464248,
            "z": 0.0
        },
        {
            "qw": 1.0,
            "qx": 0.0,
            "qy": 0.0,
            "qz": 0.0,
            "x": 0.6993287131090256,
            "y": -1.654574520209053,
            "z": 0.0
        },
        {
            "qw": 1.0,
            "qx": 0.0,
            "qy": 0.0,
            "qz": 0.0,
            "x": 0.7028496787376639,
            "y": -1.629823619571681,
            "z": 0.0
        },
        {
            "qw": 1.0,
            "qx": 0.0,
            "qy": 0.0,
            "qz": 0.0,
            "x": 0.7063729331846957,
            "y": -1.6050731004040415,
            "z": 0.0
        },
        {
            "qw": 1.0,
            "qx": 0.0,
            "qy": 0.0,
            "qz": 0.0,
            "x": 0.7098946617527986,
            "y": -1.580322581236402,
            "z": 0.0
        },
        {
            "qw": 1.0,
            "qx": 0.0,
            "qy": 0.0,
            "qz": 0.0,
            "x": 0.7134179161998304,
            "y": -1.5555720620687623,
            "z": 0.0
        },
        {
            "qw": 1.0,
            "qx": 0.0,
            "qy": 0.0,
            "qz": 0.0,
            "x": 0.7169381188890043,
            "y": -1.5308211614313905,
            "z": 0.0
        },
        {
            "qw": 1.0,
            "qx": 0.0,
            "qy": 0.0,
            "qz": 0.0,
            "x": 0.7204583215781781,
            "y": -1.5060698793242864,
            "z": 0.0
        },
        {
            "qw": 1.0,
            "qx": 0.0,
            "qy": 0.0,
            "qz": 0.0,
            "x": 0.7239747095700295,
            "y": -1.4813185972171823,
            "z": 0.0
        },
        {
            "qw": 1.0,
            "qx": 0.0,
            "qy": 0.0,
            "qz": 0.0,
            "x": 0.7274895716829519,
            "y": -1.456566933640346,
            "z": 0.0
        },
        {
            "qw": 1.0,
            "qx": 0.0,
            "qy": 0.0,
            "qz": 0.0,
            "x": 0.7310006190985519,
            "y": -1.4318148885937774,
            "z": 0.0
        },
        {
            "qw": 1.0,
            "qx": 0.0,
            "qy": 0.0,
            "qz": 0.0,
            "x": 0.7345101406352228,
            "y": -1.4070624620774765,
            "z": 0.0
        },
        {
            "qw": 1.0,
            "qx": 0.0,
            "qy": 0.0,
            "qz": 0.0,
            "x": 0.7380158474745713,
            "y": -1.3823092726217112,
            "z": 0.0
        },
        {
            "qw": 1.0,
            "qx": 0.0,
            "qy": 0.0,
            "qz": 0.0,
            "x": 0.7415200284349908,
            "y": -1.357556083165946,
            "z": 0.0
        },
        {
            "qw": 1.0,
            "qx": 0.0,
            "qy": 0.0,
            "qz": 0.0,
            "x": 0.7450226835164813,
            "y": -1.3328025122404483,
            "z": 0.0
        },
        {
            "qw": 1.0,
            "qx": 0.0,
            "qy": 0.0,
            "qz": 0.0,
            "x": 0.7485253385979718,
            "y": -1.308049322784683,
            "z": 0.0
        },
        {
            "qw": 1.0,
            "qx": 0.0,
            "qy": 0.0,
            "qz": 0.0,
            "x": 0.7520272307399978,
            "y": -1.2832957518591854,
            "z": 0.0
        },
        {
            "qw": 1.0,
            "qx": 0.0,
            "qy": 0.0,
            "qz": 0.0,
            "x": 0.7550324492906384,
            "y": -1.2584769496094736,
            "z": 0.0
        },
        {
            "qw": 1.0,
            "qx": 0.0,
            "qy": 0.0,
            "qz": 0.0,
            "x": 0.7572968536212557,
            "y": -1.2335799460646513,
            "z": 0.0
        },
        {
            "qw": 1.0,
            "qx": 0.0,
            "qy": 0.0,
            "qz": 0.0,
            "x": 0.7590218597504759,
            "y": -1.2086394549703527,
            "z": 0.0
        },
        {
            "qw": 1.0,
            "qx": 0.0,
            "qy": 0.0,
            "qz": 0.0,
            "x": 0.7603585296922688,
            "y": -1.183675312752655,
            "z": 0.0
        },
        {
            "qw": 1.0,
            "qx": 0.0,
            "qy": 0.0,
            "qz": 0.0,
            "x": 0.7614274078820245,
            "y": -1.1586982005640607,
            "z": 0.0
        },
        {
            "qw": 1.0,
            "qx": 0.0,
            "qy": 0.0,
            "qz": 0.0,
            "x": 0.7623124176608371,
            "y": -1.1337138404505538,
            "z": 0.0
        },
        {
            "qw": 1.0,
            "qx": 0.0,
            "qy": 0.0,
            "qz": 0.0,
            "x": 0.7630883270962272,
            "y": -1.1087256656397244,
            "z": 0.0
        },
        {
            "qw": 1.0,
            "qx": 0.0,
            "qy": 0.0,
            "qz": 0.0,
            "x": 0.7638016754955288,
            "y": -1.083735964949966,
            "z": 0.0
        },
        {
            "qw": 1.0,
            "qx": 0.0,
            "qy": 0.0,
            "qz": 0.0,
            "x": 0.7645165497737594,
            "y": -1.0587462642602077,
            "z": 0.0
        },
        {
            "qw": 1.0,
            "qx": 0.0,
            "qy": 0.0,
            "qz": 0.0,
            "x": 0.7652634675094987,
            "y": -1.0337573265099138,
            "z": 0.0
        },
        {
            "qw": 1.0,
            "qx": 0.0,
            "qy": 0.0,
            "qz": 0.0,
            "x": 0.7661271149833055,
            "y": -1.0087722034569424,
            "z": 0.0
        },
        {
            "qw": 1.0,
            "qx": 0.0,
            "qy": 0.0,
            "qz": 0.0,
            "x": 0.7671418244710821,
            "y": -0.9837928024499547,
            "z": 0.0
        },
        {
            "qw": 1.0,
            "qx": 0.0,
            "qy": 0.0,
            "qz": 0.0,
            "x": 0.7687539155595573,
            "y": -0.9588446819610112,
            "z": 0.0
        },
        {
            "qw": 1.0,
            "qx": 0.0,
            "qy": 0.0,
            "qz": 0.0,
            "x": 0.7711945589064726,
            "y": -0.9339644630844077,
            "z": 0.0
        },
        {
            "qw": 1.0,
            "qx": 0.0,
            "qy": 0.0,
            "qz": 0.0,
            "x": 0.774590402462934,
            "y": -0.9091960148393525,
            "z": 0.0
        },
        {
            "qw": 1.0,
            "qx": 0.0,
            "qy": 0.0,
            "qz": 0.0,
            "x": 0.7791718539472186,
            "y": -0.8846194458696175,
            "z": 0.0
        },
        {
            "qw": 1.0,
            "qx": 0.0,
            "qy": 0.0,
            "qz": 0.0,
            "x": 0.7842774448436103,
            "y": -0.8601462551973214,
            "z": 0.0
        },
        {
            "qw": 1.0,
            "qx": 0.0,
            "qy": 0.0,
            "qz": 0.0,
            "x": 0.7893853245583955,
            "y": -0.8356738274644897,
            "z": 0.0
        },
        {
            "qw": 1.0,
            "qx": 0.0,
            "qy": 0.0,
            "qz": 0.0,
            "x": 0.7944985448494322,
            "y": -0.8112021626711226,
            "z": 0.0
        },
        {
            "qw": 1.0,
            "qx": 0.0,
            "qy": 0.0,
            "qz": 0.0,
            "x": 0.7996201574745783,
            "y": -0.7867324052264166,
            "z": 0.0
        },
        {
            "qw": 1.0,
            "qx": 0.0,
            "qy": 0.0,
            "qz": 0.0,
            "x": 0.8047593177074077,
            "y": -0.7622664624790332,
            "z": 0.0
        },
        {
            "qw": 1.0,
            "qx": 0.0,
            "qy": 0.0,
            "qz": 0.0,
            "x": 0.8090058387667796,
            "y": -0.7376296212916031,
            "z": 0.0
        },
        {
            "qw": 1.0,
            "qx": 0.0,
            "qy": 0.0,
            "qz": 0.0,
            "x": 0.812760263871553,
            "y": -0.7129130529301335,
            "z": 0.0
        },
        {
            "qw": 1.0,
            "qx": 0.0,
            "qy": 0.0,
            "qz": 0.0,
            "x": 0.8164834084582822,
            "y": -0.6881919069318769,
            "z": 0.0
        },
        {
            "qw": 1.0,
            "qx": 0.0,
            "qy": 0.0,
            "qz": 0.0,
            "x": 0.8205918374745806,
            "y": -0.6635317960907798,
            "z": 0.0
        },
        {
            "qw": 1.0,
            "qx": 0.0,
            "qy": 0.0,
            "qz": 0.0,
            "x": 0.8255471292964671,
            "y": -0.6390277063701717,
            "z": 0.0
        },
        {
            "qw": 1.0,
            "qx": 0.0,
            "qy": 0.0,
            "qz": 0.0,
            "x": 0.8311356608738834,
            "y": -0.6146605642834402,
            "z": 0.0
        },
        {
            "qw": 1.0,
            "qx": 0.0,
            "qy": 0.0,
            "qz": 0.0,
            "x": 0.836728007148622,
            "y": -0.5902938036664409,
            "z": 0.0
        },
        {
            "qw": 1.0,
            "qx": 0.0,
            "qy": 0.0,
            "qz": 0.0,
            "x": 0.8423264569390767,
            "y": -0.5659289503981029,
            "z": 0.0
        },
        {
            "qw": 1.0,
            "qx": 0.0,
            "qy": 0.0,
            "qz": 0.0,
            "x": 0.8479378767004278,
            "y": -0.5415667674178906,
            "z": 0.0
        },
        {
            "qw": 1.0,
            "qx": 0.0,
            "qy": 0.0,
            "qz": 0.0,
            "x": 0.8535515852801723,
            "y": -0.5172053473771427,
            "z": 0.0
        },
        {
            "qw": 1.0,
            "qx": 0.0,
            "qy": 0.0,
            "qz": 0.0,
            "x": 0.859140879797053,
            "y": -0.4928382052904112,
            "z": 0.0
        },
        {
            "qw": 1.0,
            "qx": 0.0,
            "qy": 0.0,
            "qz": 0.0,
            "x": 0.8647034714326765,
            "y": -0.4684645782182315,
            "z": 0.0
        },
        {
            "qw": 1.0,
            "qx": 0.0,
            "qy": 0.0,
            "qz": 0.0,
            "x": 0.8702401231265071,
            "y": -0.44408561056980034,
            "z": 0.0
        },
        {
            "qw": 1.0,
            "qx": 0.0,
            "qy": 0.0,
            "qz": 0.0,
            "x": 0.8757470201812225,
            "y": -0.4196997764661887,
            "z": 0.0
        },
        {
            "qw": 1.0,
            "qx": 0.0,
            "qy": 0.0,
            "qz": 0.0,
            "x": 0.8812203478995002,
            "y": -0.3953059314981999,
            "z": 0.0
        },
        {
            "qw": 1.0,
            "qx": 0.0,
            "qy": 0.0,
            "qz": 0.0,
            "x": 0.8866524768866952,
            "y": -0.37090331272636945,
            "z": 0.0
        },
        {
            "qw": 1.0,
            "qx": 0.0,
            "qy": 0.0,
            "qz": 0.0,
            "x": 0.8920464589006656,
            "y": -0.34649230162042954,
            "z": 0.0
        },
        {
            "qw": 1.0,
            "qx": 0.0,
            "qy": 0.0,
            "qz": 0.0,
            "x": 0.8973923757283728,
            "y": -0.3220706093619867,
            "z": 0.0
        },
        {
            "qw": 1.0,
            "qx": 0.0,
            "qy": 0.0,
            "qz": 0.0,
            "x": 0.9026955679460684,
            "y": -0.29763938036023774,
            "z": 0.0
        },
        {
            "qw": 1.0,
            "qx": 0.0,
            "qy": 0.0,
            "qz": 0.0,
            "x": 0.9079506949775009,
            "y": -0.27319823314545033,
            "z": 0.0
        },
        {
            "qw": 1.0,
            "qx": 0.0,
            "qy": 0.0,
            "qz": 0.0,
            "x": 0.9131707267935667,
            "y": -0.24874907506628574,
            "z": 0.0
        },
        {
            "qw": 1.0,
            "qx": 0.0,
            "qy": 0.0,
            "qz": 0.0,
            "x": 0.9183396416655114,
            "y": -0.22428923583461824,
            "z": 0.0
        },
        {
            "qw": 1.0,
            "qx": 0.0,
            "qy": 0.0,
            "qz": 0.0,
            "x": 0.923463543109051,
            "y": -0.19981985985964457,
            "z": 0.0
        },
        {
            "qw": 1.0,
            "qx": 0.0,
            "qy": 0.0,
            "qz": 0.0,
            "x": 0.9285241205770376,
            "y": -0.1753375139137745,
            "z": 0.0
        },
        {
            "qw": 1.0,
            "qx": 0.0,
            "qy": 0.0,
            "qz": 0.0,
            "x": 0.9335297664035807,
            "y": -0.15084372387593703,
            "z": 0.0
        },
        {
            "qw": 1.0,
            "qx": 0.0,
            "qy": 0.0,
            "qz": 0.0,
            "x": 0.9384598812231388,
            "y": -0.12633467504880969,
            "z": 0.0
        },
        {
            "qw": 1.0,
            "qx": 0.0,
            "qy": 0.0,
            "qz": 0.0,
            "x": 0.9433205685514281,
            "y": -0.10181189331132146,
            "z": 0.0
        },
        {
            "qw": 1.0,
            "qx": 0.0,
            "qy": 0.0,
            "qz": 0.0,
            "x": 0.9480927549018361,
            "y": -0.07727156396614987,
            "z": 0.0
        },
        {
            "qw": 1.0,
            "qx": 0.0,
            "qy": 0.0,
            "qz": 0.0,
            "x": 0.9527787290927563,
            "y": -0.052714449952759423,
            "z": 0.0
        },
        {
            "qw": 1.0,
            "qx": 0.0,
            "qy": 0.0,
            "qz": 0.0,
            "x": 0.9572503172941538,
            "y": -0.028117663087215305,
            "z": 0.0
        },
        {
            "qw": 1.0,
            "qx": 0.0,
            "qy": 0.0,
            "qz": 0.0,
            "x": 0.9614403808331531,
            "y": -0.003471285156479098,
            "z": 0.0
        },
        {
            "qw": 1.0,
            "qx": 0.0,
            "qy": 0.0,
            "qz": 0.0,
            "x": 0.9653405273756448,
            "y": 0.021222776490787965,
            "z": 0.0
        },
        {
            "qw": 1.0,
            "qx": 0.0,
            "qy": 0.0,
            "qz": 0.0,
            "x": 0.9689629639530608,
            "y": 0.04595879980860218,
            "z": 0.0
        },
        {
            "qw": 1.0,
            "qx": 0.0,
            "qy": 0.0,
            "qz": 0.0,
            "x": 0.9723000611707562,
            "y": 0.07073487744830231,
            "z": 0.0
        },
        {
            "qw": 1.0,
            "qx": 0.0,
            "qy": 0.0,
            "qz": 0.0,
            "x": 0.9753655519390918,
            "y": 0.0955464317731014,
            "z": 0.0
        },
        {
            "qw": 1.0,
            "qx": 0.0,
            "qy": 0.0,
            "qz": 0.0,
            "x": 0.9781548586212807,
            "y": 0.12039041102514147,
            "z": 0.0
        },
        {
            "qw": 1.0,
            "qx": 0.0,
            "qy": 0.0,
            "qz": 0.0,
            "x": 0.9806817141276838,
            "y": 0.14526223756763557,
            "z": 0.0
        },
        {
            "qw": 1.0,
            "qx": 0.0,
            "qy": 0.0,
            "qz": 0.0,
            "x": 0.9829423037609786,
            "y": 0.17016000405192244,
            "z": 0.0
        },
        {
            "qw": 1.0,
            "qx": 0.0,
            "qy": 0.0,
            "qz": 0.0,
            "x": 0.9849526492499194,
            "y": 0.1950787513714829,
            "z": 0.0
        },
        {
            "qw": 1.0,
            "qx": 0.0,
            "qy": 0.0,
            "qz": 0.0,
            "x": 0.9867112247155774,
            "y": 0.22001695364738794,
            "z": 0.0
        },
        {
            "qw": 1.0,
            "qx": 0.0,
            "qy": 0.0,
            "qz": 0.0,
            "x": 0.9882332889472423,
            "y": 0.24497041471258285,
            "z": 0.0
        },
        {
            "qw": 1.0,
            "qx": 0.0,
            "qy": 0.0,
            "qz": 0.0,
            "x": 0.9895226566422366,
            "y": 0.2699372272184064,
            "z": 0.0
        },
        {
            "qw": 1.0,
            "qx": 0.0,
            "qy": 0.0,
            "qz": 0.0,
            "x": 0.9905945865898502,
            "y": 0.2949143394070006,
            "z": 0.0
        },
        {
            "qw": 1.0,
            "qx": 0.0,
            "qy": 0.0,
            "qz": 0.0,
            "x": 0.9914544193663346,
            "y": 0.31989946245997203,
            "z": 0.0
        },
        {
            "qw": 1.0,
            "qx": 0.0,
            "qy": 0.0,
            "qz": 0.0,
            "x": 0.9921227543372311,
            "y": 0.3448906890286594,
            "z": 0.0
        },
        {
            "qw": 1.0,
            "qx": 0.0,
            "qy": 0.0,
            "qz": 0.0,
            "x": 0.9926102726550425,
            "y": 0.3698857302946692,
            "z": 0.0
        },
        {
            "qw": 1.0,
            "qx": 0.0,
            "qy": 0.0,
            "qz": 0.0,
            "x": 0.992620190868081,
            "y": 0.39488573066719823,
            "z": 0.0
        },
        {
            "qw": 1.0,
            "qx": 0.0,
            "qy": 0.0,
            "qz": 0.0,
            "x": 0.9922181217702928,
            "y": 0.41988229781213704,
            "z": 0.0
        },
        {
            "qw": 1.0,
            "qx": 0.0,
            "qy": 0.0,
            "qz": 0.0,
            "x": 0.9910286991451471,
            "y": 0.4448540694244798,
            "z": 0.0
        },
        {
            "qw": 1.0,
            "qx": 0.0,
            "qy": 0.0,
            "qz": 0.0,
            "x": 0.9890435306585346,
            "y": 0.469775487032166,
            "z": 0.0
        },
        {
            "qw": 1.0,
            "qx": 0.0,
            "qy": 0.0,
            "qz": 0.0,
            "x": 0.9842881289763454,
            "y": 0.4943184866654633,
            "z": 0.0
        },
        {
            "qw": 1.0,
            "qx": 0.0,
            "qy": 0.0,
            "qz": 0.0,
            "x": 0.9769661989355996,
            "y": 0.5182229059669794,
            "z": 0.0
        },
        {
            "qw": 1.0,
            "qx": 0.0,
            "qy": 0.0,
            "qz": 0.0,
            "x": 0.9693734253849584,
            "y": 0.5420418760484722,
            "z": 0.0
        },
        {
            "qw": 1.0,
            "qx": 0.0,
            "qy": 0.0,
            "qz": 0.0,
            "x": 0.9616410339123149,
            "y": 0.5658158327015599,
            "z": 0.0
        },
        {
            "qw": 1.0,
            "qx": 0.0,
            "qy": 0.0,
            "qz": 0.0,
            "x": 0.9541916929809986,
            "y": 0.5896805791509223,
            "z": 0.0
        },
        {
            "qw": 1.0,
            "qx": 0.0,
            "qy": 0.0,
            "qz": 0.0,
            "x": 0.9471253476608581,
            "y": 0.6136605294594233,
            "z": 0.0
        },
        {
            "qw": 1.0,
            "qx": 0.0,
            "qy": 0.0,
            "qz": 0.0,
            "x": 0.9401688656236047,
            "y": 0.6376732861648975,
            "z": 0.0
        },
        {
            "qw": 1.0,
            "qx": 0.0,
            "qy": 0.0,
            "qz": 0.0,
            "x": 0.9332245906177832,
            "y": 0.6616898575676942,
            "z": 0.0
        },
        {
            "qw": 1.0,
            "qx": 0.0,
            "qy": 0.0,
            "qz": 0.0,
            "x": 0.9262284357283761,
            "y": 0.685691170181201,
            "z": 0.0
        },
        {
            "qw": 1.0,
            "qx": 0.0,
            "qy": 0.0,
            "qz": 0.0,
            "x": 0.919107158766792,
            "y": 0.7096550987609476,
            "z": 0.0
        },
        {
            "qw": 1.0,
            "qx": 0.0,
            "qy": 0.0,
            "qz": 0.0,
            "x": 0.9118455009437412,
            "y": 0.733577065670147,
            "z": 0.0
        },
        {
            "qw": 1.0,
            "qx": 0.0,
            "qy": 0.0,
            "qz": 0.0,
            "x": 0.9044549063511909,
            "y": 0.7574601226666573,
            "z": 0.0
        },
        {
            "qw": 1.0,
            "qx": 0.0,
            "qy": 0.0,
            "qz": 0.0,
            "x": 0.8969216420787802,
            "y": 0.7812981662347624,
            "z": 0.0
        },
        {
            "qw": 1.0,
            "qx": 0.0,
            "qy": 0.0,
            "qz": 0.0,
            "x": 0.8919175221311662,
            "y": 0.8057923377423322,
            "z": 0.0
        },
        {
            "qw": 1.0,
            "qx": 0.0,
            "qy": 0.0,
            "qz": 0.0,
            "x": 0.8869050098494426,
            "y": 0.8302842204315084,
            "z": 0.0
        },
        {
            "qw": 1.0,
            "qx": 0.0,
            "qy": 0.0,
            "qz": 0.0,
            "x": 0.8819085192964735,
            "y": 0.8547799178180071,
            "z": 0.0
        },
        {
            "qw": 1.0,
            "qx": 0.0,
            "qy": 0.0,
            "qz": 0.0,
            "x": 0.8768815111649246,
            "y": 0.8792695116887899,
            "z": 0.0
        },
        {
            "qw": 1.0,
            "qx": 0.0,
            "qy": 0.0,
            "qz": 0.0,
            "x": 0.8717530320845981,
            "y": 0.9037377432545668,
            "z": 0.0
        },
        {
            "qw": 1.0,
            "qx": 0.0,
            "qy": 0.0,
            "qz": 0.0,
            "x": 0.8665101120845975,
            "y": 0.9281815607574799,
            "z": 0.0
        },
        {
            "qw": 1.0,
            "qx": 0.0,
            "qy": 0.0,
            "qz": 0.0,
            "x": 0.8612740585397773,
            "y": 0.952626904139322,
            "z": 0.0
        },
        {
            "qw": 1.0,
            "qx": 0.0,
            "qy": 0.0,
            "qz": 0.0,
            "x": 0.8560074874163774,
            "y": 0.9770661440054482,
            "z": 0.0
        },
        {
            "qw": 1.0,
            "qx": 0.0,
            "qy": 0.0,
            "qz": 0.0,
            "x": 0.8507371015956551,
            "y": 1.00150462093211,
            "z": 0.0
        },
        {
            "qw": 1.0,
            "qx": 0.0,
            "qy": 0.0,
            "qz": 0.0,
            "x": 0.845436198196353,
            "y": 1.0259354684641266,
            "z": 0.0
        },
        {
            "qw": 1.0,
            "qx": 0.0,
            "qy": 0.0,
            "qz": 0.0,
            "x": 0.8429230756003108,
            "y": 1.0508095838250142,
            "z": 0.0
        },
        {
            "qw": 1.0,
            "qx": 0.0,
            "qy": 0.0,
            "qz": 0.0,
            "x": 0.8400071209670159,
            "y": 1.0756386857574967,
            "z": 0.0
        },
        {
            "qw": 1.0,
            "qx": 0.0,
            "qy": 0.0,
            "qz": 0.0,
            "x": 0.8366562908389596,
            "y": 1.1004128560485356,
            "z": 0.0
        },
        {
            "qw": 1.0,
            "qx": 0.0,
            "qy": 0.0,
            "qz": 0.0,
            "x": 0.8328965251579348,
            "y": 1.1251282800008084,
            "z": 0.0
        },
        {
            "qw": 1.0,
            "qx": 0.0,
            "qy": 0.0,
            "qz": 0.0,
            "x": 0.828701121042684,
            "y": 1.1497742764618124,
            "z": 0.0
        },
        {
            "qw": 1.0,
            "qx": 0.0,
            "qy": 0.0,
            "qz": 0.0,
            "x": 0.8240937296166067,
            "y": 1.174345504855296,
            "z": 0.0
        },
        {
            "qw": 1.0,
            "qx": 0.0,
            "qy": 0.0,
            "qz": 0.0,
            "x": 0.8190186562987947,
            "y": 1.1988251805130403,
            "z": 0.0
        },
        {
            "qw": 1.0,
            "qx": 0.0,
            "qy": 0.0,
            "qz": 0.0,
            "x": 0.8134926857574669,
            "y": 1.2232071999193295,
            "z": 0.0
        },
        {
            "qw": 1.0,
            "qx": 0.0,
            "qy": 0.0,
            "qz": 0.0,
            "x": 0.8072800696980948,
            "y": 1.247422898522359,
            "z": 0.0
        },
        {
            "qw": 1.0,
            "qx": 0.0,
            "qy": 0.0,
            "qz": 0.0,
            "x": 0.8003693640287111,
            "y": 1.2714486251987296,
            "z": 0.0
        },
        {
            "qw": 1.0,
            "qx": 0.0,
            "qy": 0.0,
            "qz": 0.0,
            "x": 0.792772012841283,
            "y": 1.2952660694012934,
            "z": 0.0
        },
        {
            "qw": 1.0,
            "qx": 0.0,
            "qy": 0.0,
            "qz": 0.0,
            "x": 0.7860070286096175,
            "y": 1.3193337577482112,
            "z": 0.0
        },
        {
            "qw": 1.0,
            "qx": 0.0,
            "qy": 0.0,
            "qz": 0.0,
            "x": 0.7787873324571137,
            "y": 1.343268694628307,
            "z": 0.0
        },
        {
            "qw": 1.0,
            "qx": 0.0,
            "qy": 0.0,
            "qz": 0.0,
            "x": 0.7710618074396507,
            "y": 1.3670449400997882,
            "z": 0.0
        },
        {
            "qw": 1.0,
            "qx": 0.0,
            "qy": 0.0,
            "qz": 0.0,
            "x": 0.7628418976491957,
            "y": 1.3906548647680097,
            "z": 0.0
        },
        {
            "qw": 1.0,
            "qx": 0.0,
            "qy": 0.0,
            "qz": 0.0,
            "x": 0.7540795378994858,
            "y": 1.4140687139938564,
            "z": 0.0
        },
        {
            "qw": 1.0,
            "qx": 0.0,
            "qy": 0.0,
            "qz": 0.0,
            "x": 0.7448510221369702,
            "y": 1.437303272445547,
            "z": 0.0
        },
        {
            "qw": 1.0,
            "qx": 0.0,
            "qy": 0.0,
            "qz": 0.0,
            "x": 0.7365021755770158,
            "y": 1.4608681836853634,
            "z": 0.0
        },
        {
            "qw": 1.0,
            "qx": 0.0,
            "qy": 0.0,
            "qz": 0.0,
            "x": 0.7278496791101929,
            "y": 1.4843224687028282,
            "z": 0.0
        },
        {
            "qw": 1.0,
            "qx": 0.0,
            "qy": 0.0,
            "qz": 0.0,
            "x": 0.7188874292207856,
            "y": 1.50766078692169,
            "z": 0.0
        },
        {
            "qw": 1.0,
            "qx": 0.0,
            "qy": 0.0,
            "qz": 0.0,
            "x": 0.7095345543255576,
            "y": 1.5308457543081886,
            "z": 0.0
        },
        {
            "qw": 1.0,
            "qx": 0.0,
            "qy": 0.0,
            "qz": 0.0,
            "x": 0.6996628805944738,
            "y": 1.553814046886771,
            "z": 0.0
        },
        {
            "qw": 1.0,
            "qx": 0.0,
            "qy": 0.0,
            "qz": 0.0,
            "x": 0.6907136006759629,
            "y": 1.5771577056818842,
            "z": 0.0
        },
        {
            "qw": 1.0,
            "qx": 0.0,
            "qy": 0.0,
            "qz": 0.0,
            "x": 0.6814560932137965,
            "y": 1.600380057102143,
            "z": 0.0
        },
        {
            "qw": 1.0,
            "qx": 0.0,
            "qy": 0.0,
            "qz": 0.0,
            "x": 0.6718354265665312,
            "y": 1.6234551612057544,
            "z": 0.0
        },
        {
            "qw": 1.0,
            "qx": 0.0,
            "qy": 0.0,
            "qz": 0.0,
            "x": 0.6615029373988932,
            "y": 1.646219748947317,
            "z": 0.0
        },
        {
            "qw": 1.0,
            "qx": 0.0,
            "qy": 0.0,
            "qz": 0.0,
            "x": 0.6503365553965637,
            "y": 1.6685876081673428,
            "z": 0.0
        },
        {
            "qw": 1.0,
            "qx": 0.0,
            "qy": 0.0,
            "qz": 0.0,
            "x": 0.6376877820147229,
            "y": 1.6901513291917922,
            "z": 0.0
        },
        {
            "qw": 1.0,
            "qx": 0.0,
            "qy": 0.0,
            "qz": 0.0,
            "x": 0.6374741589646646,
            "y": 1.7151505666248568,
            "z": 0.0
        },
        {
            "qw": 1.0,
            "qx": 0.0,
            "qy": 0.0,
            "qz": 0.0,
            "x": 0.6354622875967948,
            "y": 1.7400696954141495,
            "z": 0.0
        },
        {
            "qw": 1.0,
            "qx": 0.0,
            "qy": 0.0,
            "qz": 0.0,
            "x": 0.6313927684931855,
            "y": 1.7647362912406948,
            "z": 0.0
        },
        {
            "qw": 1.0,
            "qx": 0.0,
            "qy": 0.0,
            "qz": 0.0,
            "x": 0.6275185618924866,
            "y": 1.7894341675852843,
            "z": 0.0
        },
        {
            "qw": 1.0,
            "qx": 0.0,
            "qy": 0.0,
            "qz": 0.0,
            "x": 0.6250680003325328,
            "y": 1.8143136235224233,
            "z": 0.0
        },
        {
            "qw": 1.0,
            "qx": 0.0,
            "qy": 0.0,
            "qz": 0.0,
            "x": 0.6254006419390521,
            "y": 1.8393113350765589,
            "z": 0.0
        },
        {
            "qw": 1.0,
            "qx": 0.0,
            "qy": 0.0,
            "qz": 0.0,
            "x": 0.6292908702685054,
            "y": 1.864006922602755,
            "z": 0.0
        },
        {
            "qw": 1.0,
            "qx": 0.0,
            "qy": 0.0,
            "qz": 0.0,
            "x": 0.6362038647562827,
            "y": 1.8880326492791255,
            "z": 0.0
        },
        {
            "qw": 1.0,
            "qx": 0.0,
            "qy": 0.0,
            "qz": 0.0,
            "x": 0.6451653517062255,
            "y": 1.9113709674979873,
            "z": 0.0
        },
        {
            "qw": 1.0,
            "qx": 0.0,
            "qy": 0.0,
            "qz": 0.0,
            "x": 0.6536957778587293,
            "y": 1.9348702659438572,
            "z": 0.0
        },
        {
            "qw": 1.0,
            "qx": 0.0,
            "qy": 0.0,
            "qz": 0.0,
            "x": 0.66019678503568,
            "y": 1.959010433539902,
            "z": 0.0
        },
        {
            "qw": 1.0,
            "qx": 0.0,
            "qy": 0.0,
            "qz": 0.0,
            "x": 0.6650734940927236,
            "y": 1.9835305449892644,
            "z": 0.0
        },
        {
            "qw": 1.0,
            "qx": 0.0,
            "qy": 0.0,
            "qz": 0.0,
            "x": 0.669019417003085,
            "y": 2.0082169772418865,
            "z": 0.0
        },
        {
            "qw": 1.0,
            "qx": 0.0,
            "qy": 0.0,
            "qz": 0.0,
            "x": 0.6725625078761936,
            "y": 2.032964444651668,
            "z": 0.0
        },
        {
            "qw": 1.0,
            "qx": 0.0,
            "qy": 0.0,
            "qz": 0.0,
            "x": 0.6762505572475561,
            "y": 2.0576913126959084,
            "z": 0.0
        },
        {
            "qw": 1.0,
            "qx": 0.0,
            "qy": 0.0,
            "qz": 0.0,
            "x": 0.6804154437842271,
            "y": 2.0823418867936994,
            "z": 0.0
        },
        {
            "qw": 1.0,
            "qx": 0.0,
            "qy": 0.0,
            "qz": 0.0,
            "x": 0.6856125874163581,
            "y": 2.106795622509651,
            "z": 0.0
        },
        {
            "qw": 1.0,
            "qx": 0.0,
            "qy": 0.0,
            "qz": 0.0,
            "x": 0.6921113057749153,
            "y": 2.1309357901056956,
            "z": 0.0
        },
        {
            "qw": 1.0,
            "qx": 0.0,
            "qy": 0.0,
            "qz": 0.0,
            "x": 0.7004899069739849,
            "y": 2.154490020193009,
            "z": 0.0
        },
        {
            "qw": 1.0,
            "qx": 0.0,
            "qy": 0.0,
            "qz": 0.0,
            "x": 0.7106011436969197,
            "y": 2.1773545530044203,
            "z": 0.0
        },
        {
            "qw": 1.0,
            "qx": 0.0,
            "qy": 0.0,
            "qz": 0.0,
            "x": 0.7197083520845808,
            "y": 2.2006364137029095,
            "z": 0.0
        },
        {
            "qw": 1.0,
            "qx": 0.0,
            "qy": 0.0,
            "qz": 0.0,
            "x": 0.7286088038773642,
            "y": 2.2239983830451706,
            "z": 0.0
        },
        {
            "qw": 1.0,
            "qx": 0.0,
            "qy": 0.0,
            "qz": 0.0,
            "x": 0.7383057644710789,
            "y": 2.247040680751809,
            "z": 0.0
        },
        {
            "qw": 1.0,
            "qx": 0.0,
            "qy": 0.0,
            "qz": 0.0,
            "x": 0.7494134001346424,
            "y": 2.26943829461095,
            "z": 0.0
        },
        {
            "qw": 1.0,
            "qx": 0.0,
            "qy": 0.0,
            "qz": 0.0,
            "x": 0.760932260169568,
            "y": 2.2916261001173552,
            "z": 0.0
        },
        {
            "qw": 1.0,
            "qx": 0.0,
            "qy": 0.0,
            "qz": 0.0,
            "x": 0.771573739820326,
            "y": 2.3142480181790575,
            "z": 0.0
        },
        {
            "qw": 1.0,
            "qx": 0.0,
            "qy": 0.0,
            "qz": 0.0,
            "x": 0.782312875722539,
            "y": 2.33682415987289,
            "z": 0.0
        },
        {
            "qw": 1.0,
            "qx": 0.0,
            "qy": 0.0,
            "qz": 0.0,
            "x": 0.7939751683767895,
            "y": 2.358937197311775,
            "z": 0.0
        },
        {
            "qw": 1.0,
            "qx": 0.0,
            "qy": 0.0,
            "qz": 0.0,
            "x": 0.8065980018168375,
            "y": 2.3805161771255143,
            "z": 0.0
        },
        {
            "qw": 1.0,
            "qx": 0.0,
            "qy": 0.0,
            "qz": 0.0,
            "x": 0.8188622537085735,
            "y": 2.4023019135341315,
            "z": 0.0
        },
        {
            "qw": 1.0,
            "qx": 0.0,
            "qy": 0.0,
            "qz": 0.0,
            "x": 0.830815226298796,
            "y": 2.424258548382795,
            "z": 0.0
        },
        {
            "qw": 1.0,
            "qx": 0.0,
            "qy": 0.0,
            "qz": 0.0,
            "x": 0.8435357159902992,
            "y": 2.445781070676162,
            "z": 0.0
        },
        {
            "qw": 1.0,
            "qx": 0.0,
            "qy": 0.0,
            "qz": 0.0,
            "x": 0.8575860091684149,
            "y": 2.4664590189823343,
            "z": 0.0
        },
        {
            "qw": 1.0,
            "qx": 0.0,
            "qy": 0.0,
            "qz": 0.0,
            "x": 0.8721520494245283,
            "y": 2.4867768598612656,
            "z": 0.0
        },
        {
            "qw": 1.0,
            "qx": 0.0,
            "qy": 0.0,
            "qz": 0.0,
            "x": 0.8873070789472308,
            "y": 2.5066598252454355,
            "z": 0.0
        },
        {
            "qw": 1.0,
            "qx": 0.0,
            "qy": 0.0,
            "qz": 0.0,
            "x": 0.9034371451055563,
            "y": 2.5257607776784994,
            "z": 0.0
        },
        {
            "qw": 1.0,
            "qx": 0.0,
            "qy": 0.0,
            "qz": 0.0,
            "x": 0.9200905877365244,
            "y": 2.5444062552512605,
            "z": 0.0
        },
        {
            "qw": 1.0,
            "qx": 0.0,
            "qy": 0.0,
            "qz": 0.0,
            "x": 0.9372063716829757,
            "y": 2.562629064360692,
            "z": 0.0
        },
        {
            "qw": 1.0,
            "qx": 0.0,
            "qy": 0.0,
            "qz": 0.0,
            "x": 0.9549988829344329,
            "y": 2.5801904049544078,
            "z": 0.0
        },
        {
            "qw": 1.0,
            "qx": 0.0,
            "qy": 0.0,
            "qz": 0.0,
            "x": 0.9733292665083582,
            "y": 2.597190222102256,
            "z": 0.0
        },
        {
            "qw": 1.0,
            "qx": 0.0,
            "qy": 0.0,
            "qz": 0.0,
            "x": 0.9921486942790239,
            "y": 2.6136475892908493,
            "z": 0.0
        },
        {
            "qw": 1.0,
            "qx": 0.0,
            "qy": 0.0,
            "qz": 0.0,
            "x": 1.0112931342615639,
            "y": 2.6297250126261247,
            "z": 0.0
        },
        {
            "qw": 1.0,
            "qx": 0.0,
            "qy": 0.0,
            "qz": 0.0,
            "x": 1.0306702707807744,
            "y": 2.6455216742384664,
            "z": 0.0
        },
        {
            "qw": 1.0,
            "qx": 0.0,
            "qy": 0.0,
            "qz": 0.0,
            "x": 1.0506264783535357,
            "y": 2.6605798104491782,
            "z": 0.0
        },
        {
            "qw": 1.0,
            "qx": 0.0,
            "qy": 0.0,
            "qz": 0.0,
            "x": 1.071604261869254,
            "y": 2.6741784434643137,
            "z": 0.0
        },
        {
            "qw": 1.0,
            "qx": 0.0,
            "qy": 0.0,
            "qz": 0.0,
            "x": 1.092691145728395,
            "y": 2.687606940978867,
            "z": 0.0
        },
        {
            "qw": 1.0,
            "qx": 0.0,
            "qy": 0.0,
            "qz": 0.0,
            "x": 1.1137513267062786,
            "y": 2.7010789260428965,
            "z": 0.0
        },
        {
            "qw": 1.0,
            "qx": 0.0,
            "qy": 0.0,
            "qz": 0.0,
            "x": 1.1353020777598317,
            "y": 2.713750587608672,
            "z": 0.0
        },
        {
            "qw": 1.0,
            "qx": 0.0,
            "qy": 0.0,
            "qz": 0.0,
            "x": 1.158509933330265,
            "y": 2.723044716165134,
            "z": 0.0
        },
        {
            "qw": 1.0,
            "qx": 0.0,
            "qy": 0.0,
            "qz": 0.0,
            "x": 1.1825875398902213,
            "y": 2.7297723163630394,
            "z": 0.0
        },
        {
            "qw": 1.0,
            "qx": 0.0,
            "qy": 0.0,
            "qz": 0.0,
            "x": 1.2069275976259632,
            "y": 2.7354798664969167,
            "z": 0.0
        },
        {
            "qw": 1.0,
            "qx": 0.0,
            "qy": 0.0,
            "qz": 0.0,
            "x": 1.231349289884406,
            "y": 2.7408250203851594,
            "z": 0.0
        },
        {
            "qw": 1.0,
            "qx": 0.0,
            "qy": 0.0,
            "qz": 0.0,
            "x": 1.255635178918169,
            "y": 2.7467591635399913,
            "z": 0.0
        },
        {
            "qw": 1.0,
            "qx": 0.0,
            "qy": 0.0,
            "qz": 0.0,
            "x": 1.2796776902627585,
            "y": 2.753611122870609,
            "z": 0.0
        },
        {
            "qw": 1.0,
            "qx": 0.0,
            "qy": 0.0,
            "qz": 0.0,
            "x": 1.303119005309327,
            "y": 2.7623002404317276,
            "z": 0.0
        },
        {
            "qw": 1.0,
            "qx": 0.0,
            "qy": 0.0,
            "qz": 0.0,
            "x": 1.326351274942624,
            "y": 2.771534859709959,
            "z": 0.0
        },
        {
            "qw": 1.0,
            "qx": 0.0,
            "qy": 0.0,
            "qz": 0.0,
            "x": 1.3500756405305196,
            "y": 2.7794167873176434,
            "z": 0.0
        },
        {
            "qw": 1.0,
            "qx": 0.0,
            "qy": 0.0,
            "qz": 0.0,
            "x": 1.374065509052059,
            "y": 2.7864533779986687,
            "z": 0.0
        },
        {
            "qw": 1.0,
            "qx": 0.0,
            "qy": 0.0,
            "qz": 0.0,
            "x": 1.398096576304681,
            "y": 2.7933442472419756,
            "z": 0.0
        },
        {
            "qw": 1.0,
            "qx": 0.0,
            "qy": 0.0,
            "qz": 0.0,
            "x": 1.4219750556644044,
            "y": 2.8007493376843513,
            "z": 0.0
        },
        {
            "qw": 1.0,
            "qx": 0.0,
            "qy": 0.0,
            "qz": 0.0,
            "x": 1.4453660167063163,
            "y": 2.8095719696517563,
            "z": 0.0
        },
        {
            "qw": 1.0,
            "qx": 0.0,
            "qy": 0.0,
            "qz": 0.0,
            "x": 1.4683114211009638,
            "y": 2.8194985750242836,
            "z": 0.0
        },
        {
            "qw": 1.0,
            "qx": 0.0,
            "qy": 0.0,
            "qz": 0.0,
            "x": 1.49135677056546,
            "y": 2.8291894321022824,
            "z": 0.0
        },
        {
            "qw": 1.0,
            "qx": 0.0,
            "qy": 0.0,
            "qz": 0.0,
            "x": 1.5143540548436931,
            "y": 2.8389939671604907,
            "z": 0.0
        },
        {
            "qw": 1.0,
            "qx": 0.0,
            "qy": 0.0,
            "qz": 0.0,
            "x": 1.536966054692357,
            "y": 2.8496552832373254,
            "z": 0.0
        },
        {
            "qw": 1.0,
            "qx": 0.0,
            "qy": 0.0,
            "qz": 0.0,
            "x": 1.5589570218169229,
            "y": 2.861547983609853,
            "z": 0.0
        },
        {
            "qw": 1.0,
            "qx": 0.0,
            "qy": 0.0,
            "qz": 0.0,
            "x": 1.5805115875677984,
            "y": 2.8742120157809836,
            "z": 0.0
        },
        {
            "qw": 1.0,
            "qx": 0.0,
            "qy": 0.0,
            "qz": 0.0,
            "x": 1.6016114413978357,
            "y": 2.8876214398089246,
            "z": 0.0
        },
        {
            "qw": 1.0,
            "qx": 0.0,
            "qy": 0.0,
            "qz": 0.0,
            "x": 1.6217835608390487,
            "y": 2.9023888960836643,
            "z": 0.0
        },
        {
            "qw": 1.0,
            "qx": 0.0,
            "qy": 0.0,
            "qz": 0.0,
            "x": 1.6415719217296214,
            "y": 2.917667521799615,
            "z": 0.0
        },
        {
            "qw": 1.0,
            "qx": 0.0,
            "qy": 0.0,
            "qz": 0.0,
            "x": 1.6610314557109973,
            "y": 2.93336118658425,
            "z": 0.0
        },
        {
            "qw": 1.0,
            "qx": 0.0,
            "qy": 0.0,
            "qz": 0.0,
            "x": 1.679914207457216,
            "y": 2.9497460745237163,
            "z": 0.0
        },
        {
            "qw": 1.0,
            "qx": 0.0,
            "qy": 0.0,
            "qz": 0.0,
            "x": 1.6982560351231086,
            "y": 2.966732921700668,
            "z": 0.0
        },
        {
            "qw": 1.0,
            "qx": 0.0,
            "qy": 0.0,
            "qz": 0.0,
            "x": 1.7161874013571037,
            "y": 2.984153881432917,
            "z": 0.0
        },
        {
            "qw": 1.0,
            "qx": 0.0,
            "qy": 0.0,
            "qz": 0.0,
            "x": 1.7336236198786423,
            "y": 3.002069988877622,
            "z": 0.0
        },
        {
            "qw": 1.0,
            "qx": 0.0,
            "qy": 0.0,
            "qz": 0.0,
            "x": 1.7504090510369679,
            "y": 3.0205972108333867,
            "z": 0.0
        },
        {
            "qw": 1.0,
            "qx": 0.0,
            "qy": 0.0,
            "qz": 0.0,
            "x": 1.7665085996167136,
            "y": 3.0397225773293144,
            "z": 0.0
        },
        {
            "qw": 1.0,
            "qx": 0.0,
            "qy": 0.0,
            "qz": 0.0,
            "x": 1.7820924011184616,
            "y": 3.059271375228036,
            "z": 0.0
        },
        {
            "qw": 1.0,
            "qx": 0.0,
            "qy": 0.0,
            "qz": 0.0,
            "x": 1.79708034689844,
            "y": 3.0792802256238474,
            "z": 0.0
        },
        {
            "qw": 1.0,
            "qx": 0.0,
            "qy": 0.0,
            "qz": 0.0,
            "x": 1.8112244816306884,
            "y": 3.0998948499544667,
            "z": 0.0
        },
        {
            "qw": 1.0,
            "qx": 0.0,
            "qy": 0.0,
            "qz": 0.0,
            "x": 1.824750635396697,
            "y": 3.120919172777519,
            "z": 0.0
        },
        {
            "qw": 1.0,
            "qx": 0.0,
            "qy": 0.0,
            "qz": 0.0,
            "x": 1.837896082369923,
            "y": 3.142183821531887,
            "z": 0.0
        },
        {
            "qw": 1.0,
            "qx": 0.0,
            "qy": 0.0,
            "qz": 0.0,
            "x": 1.8503915049194006,
            "y": 3.1638368064736824,
            "z": 0.0
        },
        {
            "qw": 1.0,
            "qx": 0.0,
            "qy": 0.0,
            "qz": 0.0,
            "x": 1.8621484020672483,
            "y": 3.185900252847375,
            "z": 0.0
        },
        {
            "qw": 1.0,
            "qx": 0.0,
            "qy": 0.0,
            "qz": 0.0,
            "x": 1.873430750868181,
            "y": 3.2082101286680995,
            "z": 0.0
        },
        {
            "qw": 1.0,
            "qx": 0.0,
            "qy": 0.0,
            "qz": 0.0,
            "x": 1.8841691238309295,
            "y": 3.2307855074224676,
            "z": 0.0
        },
        {
            "qw": 1.0,
            "qx": 0.0,
            "qy": 0.0,
            "qz": 0.0,
            "x": 1.8943055375561926,
            "y": 3.2536385961419114,
            "z": 0.0
        },
        {
            "qw": 1.0,
            "qx": 0.0,
            "qy": 0.0,
            "qz": 0.0,
            "x": 1.9036515459962402,
            "y": 3.276826615286268,
            "z": 0.0
        },
        {
            "qw": 1.0,
            "qx": 0.0,
            "qy": 0.0,
            "qz": 0.0,
            "x": 1.912186549785531,
            "y": 3.300324387853209,
            "z": 0.0
        },
        {
            "qw": 1.0,
            "qx": 0.0,
            "qy": 0.0,
            "qz": 0.0,
            "x": 1.9198258626435063,
            "y": 3.324128099145412,
            "z": 0.0
        },
        {
            "qw": 1.0,
            "qx": 0.0,
            "qy": 0.0,
            "qz": 0.0,
            "x": 1.9267007101580589,
            "y": 3.3481645069742854,
            "z": 0.0
        },
        {
            "qw": 1.0,
            "qx": 0.0,
            "qy": 0.0,
            "qz": 0.0,
            "x": 1.932672237346651,
            "y": 3.3724412407344744,
            "z": 0.0
        },
        {
            "qw": 1.0,
            "qx": 0.0,
            "qy": 0.0,
            "qz": 0.0,
            "x": 1.9378899803443232,
            "y": 3.396890398813639,
            "z": 0.0
        },
        {
            "qw": 1.0,
            "qx": 0.0,
            "qy": 0.0,
            "qz": 0.0,
            "x": 1.942207454773893,
            "y": 3.4215142700301726,
            "z": 0.0
        },
        {
            "qw": 1.0,
            "qx": 0.0,
            "qy": 0.0,
            "qz": 0.0,
            "x": 1.9454163781615534,
            "y": 3.446307513807824,
            "z": 0.0
        },
        {
            "qw": 1.0,
            "qx": 0.0,
            "qy": 0.0,
            "qz": 0.0,
            "x": 1.9477921716539868,
            "y": 3.471194599139608,
            "z": 0.0
        },
        {
            "qw": 1.0,
            "qx": 0.0,
            "qy": 0.0,
            "qz": 0.0,
            "x": 1.9496064417005528,
            "y": 3.4961289867181904,
            "z": 0.0
        },
        {
            "qw": 1.0,
            "qx": 0.0,
            "qy": 0.0,
            "qz": 0.0,
            "x": 1.9510277979229045,
            "y": 3.5210885512991013,
            "z": 0.0
        },
        {
            "qw": 1.0,
            "qx": 0.0,
            "qy": 0.0,
            "qz": 0.0,
            "x": 1.9523278467704017,
            "y": 3.546054219395728,
            "z": 0.0
        },
        {
            "qw": 1.0,
            "qx": 0.0,
            "qy": 0.0,
            "qz": 0.0,
            "x": 1.9535470240346626,
            "y": 3.571024465129142,
            "z": 0.0
        },
        {
            "qw": 1.0,
            "qx": 0.0,
            "qy": 0.0,
            "qz": 0.0,
            "x": 1.9547570460253496,
            "y": 3.59599547380202,
            "z": 0.0
        },
        {
            "qw": 1.0,
            "qx": 0.0,
            "qy": 0.0,
            "qz": 0.0,
            "x": 1.9559327357401344,
            "y": 3.6209680083538274,
            "z": 0.0
        },
        {
            "qw": 1.0,
            "qx": 0.0,
            "qy": 0.0,
            "qz": 0.0,
            "x": 1.9572106593431613,
            "y": 3.645935202329383,
            "z": 0.0
        },
        {
            "qw": 1.0,
            "qx": 0.0,
            "qy": 0.0,
            "qz": 0.0,
            "x": 1.9585313075561999,
            "y": 3.6709001074865455,
            "z": 0.0
        },
        {
            "qw": 1.0,
            "qx": 0.0,
            "qy": 0.0,
            "qz": 0.0,
            "x": 1.9569390528938015,
            "y": 3.695849753854418,
            "z": 0.0
        },
        {
            "qw": 1.0,
            "qx": 0.0,
            "qy": 0.0,
            "qz": 0.0,
            "x": 1.9526963465317522,
            "y": 3.720486595041848,
            "z": 0.0
        },
        {
            "qw": 1.0,
            "qx": 0.0,
            "qy": 0.0,
            "qz": 0.0,
            "x": 1.9461556665026478,
            "y": 3.7446160814853897,
            "z": 0.0
        },
        {
            "qw": 1.0,
            "qx": 0.0,
            "qy": 0.0,
            "qz": 0.0,
            "x": 1.9374589195468843,
            "y": 3.7680543447741,
            "z": 0.0
        },
        {
            "qw": 1.0,
            "qx": 0.0,
            "qy": 0.0,
            "qz": 0.0,
            "x": 1.9262299765084663,
            "y": 3.7903909234760818,
            "z": 0.0
        },
        {
            "qw": 1.0,
            "qx": 0.0,
            "qy": 0.0,
            "qz": 0.0,
            "x": 1.9124139057459502,
            "y": 3.8112260373119398,
            "z": 0.0
        },
        {
            "qw": 1.0,
            "qx": 0.0,
            "qy": 0.0,
            "qz": 0.0,
            "x": 1.9000001177191734,
            "y": 3.8500001467764378,
            "z": 0.0
        }
    ],
    "start_position": [
        1.9333022895055556,
        3.8952786207050853,
        0.0
    ]
}